{
 "schema_version": 1,
 "book": "1-ne",
 "chapters": {
  "1": [
   {
    "id": "1-ne-1-fb-3",
    "type": "fill_blank",
    "after_verse": 3,
    "verse": 3,
    "template": "And I know that the record which I make is true; and I make it with mine own hand; and I make it {0} to my knowledge.",
    "blanks": [
     "according"
    ],
    "distractors": [
     "abominations",
     "commencement",
     "nevertheless"
    ]
   },
   {
    "id": "1-ne-1-cur-5",
    "after_verse": 5,
    "type": "curiosity",
    "title": "A book from heaven",
    "text": "In the vision, Lehi is given a book and reads it; written in it are the destruction of Jerusalem and the coming of a Messiah to redeem mankind."
   },
   {
    "id": "1-ne-1-mc-9",
    "after_verse": 9,
    "type": "multiple_choice",
    "question": "In Lehi’s vision, the brightness of the One descending from heaven was above that of what?",
    "options": [
     "The sun at noonday",
     "The moon",
     "The stars",
     "A torch"
    ],
    "answer": 0
   },
   {
    "id": "1-ne-1-fb-13",
    "type": "fill_blank",
    "after_verse": 13,
    "verse": 13,
    "template": "And he read, saying: Wo, wo, unto Jerusalem, for I have seen thine abominations! Yea, and many things did my father read concerning Jerusalem —that it should be destroyed, and the inhabitants thereof; many should perish by the sword, and many should be carried away captive into {0}.",
    "blanks": [
     "Babylon"
    ],
    "distractors": [
     "Egypt",
     "Nineveh",
     "Assyria"
    ]
   },
   {
    "id": "1-ne-1-fb-20",
    "after_verse": 20,
    "type": "fill_blank",
    "verse": 20,
    "template": "the tender {0} of the Lord are over all those whom he hath chosen",
    "blanks": [
     "mercies"
    ],
    "distractors": [
     "judgments",
     "words",
     "commandments"
    ]
   }
  ],
  "2": [
   {
    "id": "1-ne-2-fb-3",
    "type": "fill_blank",
    "after_verse": 3,
    "verse": 3,
    "template": "And it came to pass that he was {0} unto the word of the Lord, wherefore he did as the Lord commanded him.",
    "blanks": [
     "obedient"
    ],
    "distractors": [
     "faithful",
     "rebellious",
     "stubborn"
    ]
   },
   {
    "id": "1-ne-2-cur-4",
    "after_verse": 4,
    "type": "curiosity",
    "title": "Leaving everything behind",
    "text": "Lehi obeyed at once: he departed into the wilderness and left his house, his inheritance, his gold, his silver, and his precious things, taking only his family and provisions."
   },
   {
    "id": "1-ne-2-fb-8",
    "type": "fill_blank",
    "after_verse": 8,
    "verse": 8,
    "template": "And it came to pass that he called the name of the river, {0}, and it emptied into the Red Sea; and the valley was in the borders near the mouth thereof.",
    "blanks": [
     "Laman"
    ],
    "distractors": [
     "Lemuel",
     "Nephi",
     "Ishmael"
    ]
   },
   {
    "id": "1-ne-2-mc-13",
    "after_verse": 13,
    "type": "multiple_choice",
    "question": "Which two of Lehi’s sons murmured against him for leaving Jerusalem?",
    "options": [
     "Laman and Lemuel",
     "Sam and Nephi",
     "Nephi and Lemuel",
     "Laman and Sam"
    ],
    "answer": 0
   },
   {
    "id": "1-ne-2-fb-20",
    "after_verse": 20,
    "type": "fill_blank",
    "verse": 20,
    "template": "ye shall prosper, and shall be led to a land of {0}",
    "blanks": [
     "promise"
    ],
    "distractors": [
     "rest",
     "inheritance",
     "refuge"
    ]
   },
   {
    "id": "1-ne-2-fb-22",
    "type": "fill_blank",
    "after_verse": 22,
    "verse": 22,
    "template": "And inasmuch as thou shalt keep my {0}, thou shalt be made a ruler and a teacher over thy brethren.",
    "blanks": [
     "commandments"
    ],
    "distractors": [
     "precepts",
     "statutes",
     "covenants"
    ]
   }
  ],
  "3": [
   {
    "id": "1-ne-3-cur-3",
    "type": "curiosity",
    "after_verse": 3,
    "title": "The brass plates",
    "text": "The brass plates held the record of the Jews and the genealogy of Lehi's forefathers, engraven on metal. Nephi's people would keep and add to such records for a thousand years."
   },
   {
    "id": "1-ne-3-mc-4",
    "type": "multiple_choice",
    "after_verse": 4,
    "question": "What did the Lord command Lehi's sons to obtain from Laban?",
    "options": [
     "The records engraven on the plates of brass",
     "A flock of sheep",
     "A ship to cross the sea",
     "The keys of the temple"
    ],
    "answer": 0
   },
   {
    "id": "1-ne-3-fb-7",
    "type": "fill_blank",
    "after_verse": 7,
    "verse": 7,
    "template": "I will go and do the things which the Lord hath {0}",
    "blanks": [
     "commanded"
    ],
    "distractors": [
     "spoken",
     "required",
     "prepared"
    ]
   },
   {
    "id": "1-ne-3-mc-11",
    "type": "multiple_choice",
    "after_verse": 11,
    "question": "When they cast lots, upon whom did the lot fall to go in unto Laban first?",
    "options": [
     "Laman",
     "Lemuel",
     "Nephi",
     "Sam"
    ],
    "answer": 0
   },
   {
    "id": "1-ne-3-fb-19",
    "type": "fill_blank",
    "after_verse": 19,
    "verse": 19,
    "template": "that we may preserve unto our children the {0} of our fathers",
    "blanks": [
     "language"
    ],
    "distractors": [
     "records",
     "words",
     "commandments"
    ]
   },
   {
    "id": "1-ne-3-mc-25",
    "type": "multiple_choice",
    "after_verse": 25,
    "question": "Why did Laban thrust the brothers out and send servants to slay them?",
    "options": [
     "He lusted after their gold, silver, and precious things",
     "He feared the prophets",
     "He wished to keep the city safe",
     "He wanted to join Lehi"
    ],
    "answer": 0
   },
   {
    "id": "1-ne-3-mc-27",
    "type": "multiple_choice",
    "after_verse": 27,
    "question": "Where did Nephi and his brothers hide after fleeing the servants of Laban?",
    "options": [
     "In the cavity of a rock",
     "In their father's tent",
     "In the temple",
     "In a ship"
    ],
    "answer": 0
   },
   {
    "id": "1-ne-3-cur-29",
    "type": "curiosity",
    "after_verse": 29,
    "title": "An angel intervenes",
    "text": "As Laman and Lemuel beat their younger brothers with a rod, an angel of the Lord appeared and rebuked them, declaring that Nephi had been chosen to be a ruler over them, and that the Lord would deliver Laban into their hands."
   },
   {
    "id": "1-ne-3-mc-31",
    "type": "multiple_choice",
    "after_verse": 31,
    "question": "Doubting again, how many men did Laman and Lemuel say Laban could command?",
    "options": [
     "Fifty",
     "Ten",
     "A hundred",
     "A thousand"
    ],
    "answer": 0
   }
  ],
  "4": [
   {
    "id": "1-ne-4-cur-2",
    "type": "curiosity",
    "after_verse": 2,
    "title": "Be strong like Moses",
    "text": "To give his brothers courage, Nephi recalls the Exodus: Moses spoke to the Red Sea and it divided, their fathers crossed on dry ground, and Pharaoh's armies were drowned. If God could do that, surely he could deliver them from Laban."
   },
   {
    "id": "1-ne-4-mc-3",
    "type": "multiple_choice",
    "after_verse": 3,
    "question": "Which prophet's example did Nephi use to urge his brothers to be strong?",
    "options": [
     "Moses",
     "Abraham",
     "Isaiah",
     "Noah"
    ],
    "answer": 0
   },
   {
    "id": "1-ne-4-fb-6",
    "type": "fill_blank",
    "after_verse": 6,
    "verse": 6,
    "template": "And I was led by the {0}, not knowing beforehand the things which I should do.",
    "blanks": [
     "Spirit"
    ],
    "distractors": [
     "Lord",
     "angel",
     "sword"
    ]
   },
   {
    "id": "1-ne-4-fb-13",
    "type": "fill_blank",
    "after_verse": 13,
    "verse": 13,
    "template": "It is better that one man should perish than that a {0} should dwindle and perish in unbelief.",
    "blanks": [
     "nation"
    ],
    "distractors": [
     "people",
     "city",
     "kingdom"
    ]
   },
   {
    "id": "1-ne-4-mc-18",
    "type": "multiple_choice",
    "after_verse": 18,
    "question": "Which item of Laban's did Nephi take for himself?",
    "options": [
     "Laban's own sword",
     "A staff",
     "A stone",
     "A bow"
    ],
    "answer": 0
   },
   {
    "id": "1-ne-4-mc-21",
    "type": "multiple_choice",
    "after_verse": 21,
    "question": "Why did Laban's servant suppose Nephi to be his master Laban?",
    "options": [
     "Nephi wore Laban's garments and sword",
     "Nephi spoke Egyptian",
     "It was too dark to see",
     "The servant was drunken"
    ],
    "answer": 0
   },
   {
    "id": "1-ne-4-fb-28",
    "type": "fill_blank",
    "after_verse": 28,
    "verse": 28,
    "template": "when Laman saw me he was exceedingly {0}",
    "blanks": [
     "frightened"
    ],
    "distractors": [
     "sorrowful",
     "wroth",
     "glad"
    ]
   },
   {
    "id": "1-ne-4-mp-35",
    "type": "match_pairs",
    "after_verse": 35,
    "pairs": [
     {
      "left": "Laban",
      "right": "Keeper of the brass plates, slain by Nephi"
     },
     {
      "left": "Zoram",
      "right": "Servant of Laban who swore to join Lehi's family"
     },
     {
      "left": "Nephi",
      "right": "The son who obtained the records"
     },
     {
      "left": "Laman",
      "right": "Eldest brother who murmured and doubted"
     }
    ]
   },
   {
    "id": "1-ne-4-mc-38",
    "type": "multiple_choice",
    "after_verse": 38,
    "question": "Besides Zoram, what did they take with them into the wilderness to their father's tent?",
    "options": [
     "The plates of brass",
     "Laban's treasure",
     "A flock of animals",
     "The keys of the city"
    ],
    "answer": 0
   }
  ],
  "5": [
   {
    "id": "1-ne-5-cur-1",
    "type": "curiosity",
    "after_verse": 1,
    "title": "Sariah, a named matriarch",
    "text": "Sariah, Lehi's wife, is one of the few women named in the Book of Mormon. Fearing her sons had perished, she had mourned and complained; their safe return turned her grief into faith and rejoicing."
   },
   {
    "id": "1-ne-5-fb-4",
    "type": "fill_blank",
    "after_verse": 4,
    "verse": 4,
    "template": "I know that I am a {0} man",
    "blanks": [
     "visionary"
    ],
    "distractors": [
     "righteous",
     "faithful",
     "mighty"
    ]
   },
   {
    "id": "1-ne-5-mc-9",
    "type": "multiple_choice",
    "after_verse": 9,
    "question": "After the sons returned safely, what did the family offer to the Lord in thanksgiving?",
    "options": [
     "Sacrifice and burnt offerings",
     "Gold and silver",
     "The plates of brass",
     "A new tent"
    ],
    "answer": 0
   },
   {
    "id": "1-ne-5-fb-11",
    "type": "fill_blank",
    "after_verse": 11,
    "verse": 11,
    "template": "they did contain the five books of {0}",
    "blanks": [
     "Moses"
    ],
    "distractors": [
     "Abraham",
     "Jacob",
     "Joseph"
    ]
   },
   {
    "id": "1-ne-5-cur-14",
    "type": "curiosity",
    "after_verse": 14,
    "title": "Descendants of Joseph",
    "text": "The genealogy revealed that Lehi descended from Joseph — the son of Jacob who was sold into Egypt and later preserved his family from famine. Even Laban, keeper of the plates, was of the same lineage."
   },
   {
    "id": "1-ne-5-fb-19",
    "type": "fill_blank",
    "after_verse": 19,
    "verse": 19,
    "template": "these plates of brass should never {0}",
    "blanks": [
     "perish"
    ],
    "distractors": [
     "prosper",
     "wander",
     "return"
    ]
   },
   {
    "id": "1-ne-5-mc-21",
    "type": "multiple_choice",
    "after_verse": 21,
    "question": "Why were the records of such great worth to Nephi's family?",
    "options": [
     "So they could preserve the commandments of the Lord unto their children",
     "Because they were made of gold",
     "Because they listed their riches",
     "Because they showed the way back to Jerusalem"
    ],
    "answer": 0
   }
  ],
  "6": [
   {
    "id": "1-ne-6-cur-2",
    "type": "curiosity",
    "after_verse": 2,
    "title": "Why Nephi omits the genealogy",
    "text": "Nephi deliberately leaves the full genealogy on his father's record, since the space on his own plates is precious. He keeps only what is of worth: it is enough, he says, to know that they are descendants of Joseph."
   },
   {
    "id": "1-ne-6-fb-4",
    "type": "fill_blank",
    "after_verse": 4,
    "verse": 4,
    "template": "and the God of Jacob, and be {0}",
    "blanks": [
     "saved"
    ],
    "distractors": [
     "blessed",
     "gathered",
     "redeemed"
    ]
   },
   {
    "id": "1-ne-6-mc-6",
    "type": "multiple_choice",
    "after_verse": 6,
    "question": "What does Nephi command his seed concerning these plates?",
    "options": [
     "Not to fill them with things of no worth to the children of men",
     "To bury them in the wilderness",
     "To copy them onto gold",
     "To give them to the Jews"
    ],
    "answer": 0
   }
  ],
  "7": [
   {
    "id": "1-ne-7-cur-2",
    "type": "curiosity",
    "after_verse": 2,
    "title": "Ishmael's family",
    "text": "Lehi sends his sons back for Ishmael's household so they can marry. Ishmael's sons and daughters would become ancestors of the Lamanites and Nephites alongside Lehi's children."
   },
   {
    "id": "1-ne-7-mc-5",
    "type": "multiple_choice",
    "after_verse": 5,
    "question": "Whom did Nephi and his brethren return to Jerusalem to bring into the wilderness?",
    "options": [
     "Ishmael and his family",
     "Laban and his servants",
     "The elders of the Jews",
     "Jeremiah the prophet"
    ],
    "answer": 0
   },
   {
    "id": "1-ne-7-mc-6",
    "type": "multiple_choice",
    "after_verse": 6,
    "question": "Who joined Laman and Lemuel in rebelling during the journey?",
    "options": [
     "Two daughters and the two sons of Ishmael and their families",
     "Sariah and Sam",
     "Zoram and Nephi",
     "The servants of Laban"
    ],
    "answer": 0
   },
   {
    "id": "1-ne-7-fb-11",
    "type": "fill_blank",
    "after_verse": 11,
    "verse": 11,
    "template": "in delivering us out of the hands of {0}",
    "blanks": [
     "Laban"
    ],
    "distractors": [
     "Ishmael",
     "Lemuel",
     "Laman"
    ]
   },
   {
    "id": "1-ne-7-mc-16",
    "type": "multiple_choice",
    "after_verse": 16,
    "question": "How did his brothers respond when Nephi rebuked them?",
    "options": [
     "They bound him with cords and sought his life",
     "They wept and repented at once",
     "They abandoned the journey",
     "They prayed with him"
    ],
    "answer": 0
   },
   {
    "id": "1-ne-7-cur-18",
    "type": "curiosity",
    "after_verse": 18,
    "title": "Bands loosed by faith",
    "text": "When Nephi prayed for strength according to his faith, the cords binding his hands and feet fell away. He repeatedly turned to prayer in moments of danger throughout his record."
   },
   {
    "id": "1-ne-7-mc-22",
    "type": "multiple_choice",
    "after_verse": 22,
    "question": "What did the families do when they reached Lehi's tent?",
    "options": [
     "Gave thanks and offered sacrifice and burnt offerings",
     "Began building a ship",
     "Returned to Jerusalem",
     "Cast lots for the records"
    ],
    "answer": 0
   }
  ],
  "8": [
   {
    "id": "1-ne-8-cur-2",
    "type": "curiosity",
    "after_verse": 2,
    "title": "The tree of life vision",
    "text": "Lehi's dream is the Book of Mormon's most famous vision. Each element - the tree, the iron rod, the path, the mist, and the building - carries meaning that Nephi will later explain."
   },
   {
    "id": "1-ne-8-mc-5",
    "type": "multiple_choice",
    "after_verse": 5,
    "question": "Who came and stood before Lehi in his dream, bidding him follow?",
    "options": [
     "A man dressed in a white robe",
     "An angel with a sword",
     "His son Nephi",
     "Laban"
    ],
    "answer": 0
   },
   {
    "id": "1-ne-8-mc-10",
    "type": "multiple_choice",
    "after_verse": 10,
    "question": "What did Lehi behold whose fruit was desirable to make one happy?",
    "options": [
     "A tree",
     "A fountain",
     "A great building",
     "A rod of iron"
    ],
    "answer": 0
   },
   {
    "id": "1-ne-8-fb-11",
    "type": "fill_blank",
    "after_verse": 11,
    "verse": 11,
    "template": "I beheld that the fruit thereof was {0}",
    "blanks": [
     "white"
    ],
    "distractors": [
     "red",
     "golden",
     "dark"
    ]
   },
   {
    "id": "1-ne-8-mc-19",
    "type": "multiple_choice",
    "after_verse": 19,
    "question": "What did Lehi behold extending along the bank of the river, leading to the tree?",
    "options": [
     "A rod of iron",
     "A wall of stone",
     "A river of fire",
     "A golden chain"
    ],
    "answer": 0
   },
   {
    "id": "1-ne-8-mc-23",
    "type": "multiple_choice",
    "after_verse": 23,
    "question": "What arose that caused those on the path to lose their way?",
    "options": [
     "A mist of darkness",
     "A great flood",
     "A band of robbers",
     "A storm of fire"
    ],
    "answer": 0
   },
   {
    "id": "1-ne-8-mc-27",
    "type": "multiple_choice",
    "after_verse": 27,
    "question": "What were the people in the great and spacious building doing?",
    "options": [
     "Mocking and pointing fingers at those partaking of the fruit",
     "Singing praises to God",
     "Building a ship",
     "Holding to the rod of iron"
    ],
    "answer": 0
   },
   {
    "id": "1-ne-8-cur-30",
    "type": "curiosity",
    "after_verse": 30,
    "title": "Holding to the rod",
    "text": "Lehi saw that only those who held continually to the iron rod reached the tree and its fruit. Others let go and were lost in the mist or wandered toward the great and spacious building."
   },
   {
    "id": "1-ne-8-mp-31",
    "type": "match_pairs",
    "after_verse": 31,
    "pairs": [
     {
      "left": "Rod of iron",
      "right": "Led to the tree of life"
     },
     {
      "left": "Mist of darkness",
      "right": "Caused many to lose their way"
     },
     {
      "left": "Great and spacious building",
      "right": "Filled with people mocking"
     },
     {
      "left": "Man in a white robe",
      "right": "Bade Lehi to follow him"
     }
    ]
   },
   {
    "id": "1-ne-8-mc-35",
    "type": "multiple_choice",
    "after_verse": 35,
    "question": "In Lehi's dream, who partook not of the fruit?",
    "options": [
     "Laman and Lemuel",
     "Nephi and Sam",
     "Sariah",
     "Zoram"
    ],
    "answer": 0
   },
   {
    "id": "1-ne-8-fb-38",
    "type": "fill_blank",
    "after_verse": 38,
    "verse": 38,
    "template": "to keep the {0} of the Lord",
    "blanks": [
     "commandments"
    ],
    "distractors": [
     "words",
     "statutes",
     "covenants"
    ]
   }
  ],
  "9": [
   {
    "id": "1-ne-9-cur-3",
    "type": "curiosity",
    "after_verse": 3,
    "title": "Two sets of plates",
    "text": "Nephi kept two records: the small plates (these), devoted to sacred and prophetic matters, and the large plates, devoted to the reign of the kings, the wars, and the history of his people."
   },
   {
    "id": "1-ne-9-mc-4",
    "type": "multiple_choice",
    "after_verse": 4,
    "question": "What did Nephi say should be engraven on the 'other plates'?",
    "options": [
     "The reign of the kings, and the wars and contentions of his people",
     "The ministry and teachings of his people",
     "His genealogy back to Joseph",
     "Lehi's dream of the tree of life"
    ],
    "answer": 0
   },
   {
    "id": "1-ne-9-mc-5",
    "type": "multiple_choice",
    "after_verse": 5,
    "question": "Why did Nephi say the Lord commanded him to make these plates?",
    "options": [
     "For a wise purpose in the Lord, which Nephi did not know",
     "To record the wars of his people",
     "To list his genealogy",
     "To replace the brass plates"
    ],
    "answer": 0
   },
   {
    "id": "1-ne-9-fb-6",
    "type": "fill_blank",
    "after_verse": 6,
    "verse": 6,
    "template": "he hath all {0} unto the fulfilling of all his words",
    "blanks": [
     "power"
    ],
    "distractors": [
     "wisdom",
     "knowledge",
     "judgment"
    ]
   }
  ],
  "10": [
   {
    "id": "1-ne-10-mc-3",
    "type": "multiple_choice",
    "after_verse": 3,
    "question": "What did Lehi prophesy concerning the Jews after Jerusalem's destruction?",
    "options": [
     "They would be carried captive to Babylon and later return to their land",
     "They would never again possess their land",
     "They would be destroyed entirely",
     "They would conquer Babylon"
    ],
    "answer": 0
   },
   {
    "id": "1-ne-10-fb-4",
    "type": "fill_blank",
    "after_verse": 4,
    "verse": 4,
    "template": "from the time that my father left {0}",
    "blanks": [
     "Jerusalem"
    ],
    "distractors": [
     "Babylon",
     "Bethabara",
     "Jericho"
    ]
   },
   {
    "id": "1-ne-10-cur-7",
    "type": "curiosity",
    "after_verse": 7,
    "title": "A prophet to prepare the way",
    "text": "About 600 years beforehand, Lehi foresaw John the Baptist, who would cry in the wilderness, baptize with water, and baptize the Messiah himself."
   },
   {
    "id": "1-ne-10-mc-8",
    "type": "multiple_choice",
    "after_verse": 8,
    "question": "What did Lehi say the prophet would cry in the wilderness?",
    "options": [
     "Prepare ye the way of the Lord, and make his paths straight",
     "Repent, for the kingdom is at hand",
     "Babylon is fallen",
     "Come and see the Lamb of God"
    ],
    "answer": 0
   },
   {
    "id": "1-ne-10-mc-11",
    "type": "multiple_choice",
    "after_verse": 11,
    "question": "After the Messiah would be slain, what did Lehi prophesy he would do?",
    "options": [
     "Rise from the dead and manifest himself to the Gentiles by the Holy Ghost",
     "Remain in the tomb forever",
     "Return only to the Jews",
     "Destroy Jerusalem"
    ],
    "answer": 0
   },
   {
    "id": "1-ne-10-fb-12",
    "type": "fill_blank",
    "after_verse": 12,
    "verse": 12,
    "template": "compared like unto an {0} tree",
    "blanks": [
     "olive"
    ],
    "distractors": [
     "fig",
     "palm",
     "cedar"
    ]
   },
   {
    "id": "1-ne-10-mp-16",
    "type": "match_pairs",
    "after_verse": 16,
    "pairs": [
     {
      "left": "Messiah",
      "right": "A Savior of the world"
     },
     {
      "left": "Lamb of God",
      "right": "Takes away the sins of the world"
     },
     {
      "left": "Bethabara",
      "right": "Where the prophet would baptize"
     },
     {
      "left": "Olive tree",
      "right": "Symbol of the house of Israel"
     }
    ]
   },
   {
    "id": "1-ne-10-cur-17",
    "type": "curiosity",
    "after_verse": 17,
    "title": "Nephi seeks to see for himself",
    "text": "Hearing his father's vision, Nephi desired to see and know the same things by the power of the Holy Ghost - the gift of God to all who diligently seek him. His own vision follows in the next chapters."
   },
   {
    "id": "1-ne-10-mc-19",
    "type": "multiple_choice",
    "after_verse": 19,
    "question": "What did Nephi teach about those who diligently seek the Lord?",
    "options": [
     "He that diligently seeketh shall find, and the mysteries of God shall be unfolded unto them",
     "Only prophets can know the mysteries of God",
     "The Lord changes with each generation",
     "The way is open only to the house of Israel"
    ],
    "answer": 0
   },
   {
    "id": "1-ne-10-mc-21",
    "type": "multiple_choice",
    "after_verse": 21,
    "question": "What did Nephi teach about the unclean and the judgment-seat of God?",
    "options": [
     "No unclean thing can dwell with God, so the unclean must be cast off",
     "The unclean are cleansed automatically at judgment",
     "God dwells with all people regardless",
     "Only the Jews face the judgment-seat"
    ],
    "answer": 0
   }
  ],
  "11": [
   {
    "id": "1-ne-11-cur-1",
    "type": "curiosity",
    "after_verse": 1,
    "title": "Caught up into a mountain",
    "text": "Pondering his father's words, Nephi was caught away by the Spirit to an exceedingly high mountain he had never seen. There he was shown the same vision of the tree of life, with its full interpretation."
   },
   {
    "id": "1-ne-11-mc-4",
    "type": "multiple_choice",
    "after_verse": 4,
    "question": "When Nephi desired to see his father's vision, what did the Spirit ask if he believed his father had seen?",
    "options": [
     "The tree of which his father had spoken",
     "An angel with a sword",
     "The city of Babylon",
     "The plates of brass"
    ],
    "answer": 0
   },
   {
    "id": "1-ne-11-mc-7",
    "type": "multiple_choice",
    "after_verse": 7,
    "question": "What sign was given Nephi - whom would he behold descending out of heaven?",
    "options": [
     "A man, the Son of God",
     "An army of angels",
     "His father Lehi",
     "The prophet Jeremiah"
    ],
    "answer": 0
   },
   {
    "id": "1-ne-11-mc-13",
    "type": "multiple_choice",
    "after_verse": 13,
    "question": "In what city did Nephi behold a virgin, exceedingly fair and white?",
    "options": [
     "Nazareth",
     "Jerusalem",
     "Bethlehem",
     "Babylon"
    ],
    "answer": 0
   },
   {
    "id": "1-ne-11-mc-16",
    "type": "multiple_choice",
    "after_verse": 16,
    "question": "What did the angel ask Nephi if he understood?",
    "options": [
     "The condescension of God",
     "The fall of Babylon",
     "The law of Moses",
     "The genealogy of his fathers"
    ],
    "answer": 0
   },
   {
    "id": "1-ne-11-cur-18",
    "type": "curiosity",
    "after_verse": 18,
    "title": "The mother of the Son of God",
    "text": "The angel showed Nephi that the virgin of Nazareth was the mother of the Son of God after the manner of the flesh - answering the question about the 'condescension of God,' that God Himself would come down to dwell among men."
   },
   {
    "id": "1-ne-11-mc-21",
    "type": "multiple_choice",
    "after_verse": 21,
    "question": "As the virgin bore a child in her arms, what did the angel declare?",
    "options": [
     "Behold the Lamb of God, the Son of the Eternal Father",
     "Behold the prophet of the Lord",
     "Behold the king of the Jews",
     "Behold the angel of light"
    ],
    "answer": 0
   },
   {
    "id": "1-ne-11-fb-22",
    "type": "fill_blank",
    "after_verse": 22,
    "verse": 22,
    "template": "it is the {0} of God, which sheddeth itself abroad",
    "blanks": [
     "love"
    ],
    "distractors": [
     "power",
     "word",
     "glory"
    ]
   },
   {
    "id": "1-ne-11-mc-27",
    "type": "multiple_choice",
    "after_verse": 27,
    "question": "In Nephi's vision, who baptized the Lamb of God?",
    "options": [
     "The prophet who should prepare the way before him",
     "An angel from heaven",
     "His disciples",
     "The high priest"
    ],
    "answer": 0
   },
   {
    "id": "1-ne-11-fb-28",
    "type": "fill_blank",
    "after_verse": 28,
    "verse": 28,
    "template": "in power and great {0}",
    "blanks": [
     "glory"
    ],
    "distractors": [
     "joy",
     "mercy",
     "light"
    ]
   },
   {
    "id": "1-ne-11-mc-33",
    "type": "multiple_choice",
    "after_verse": 33,
    "question": "What did Nephi see happen to the Lamb of God?",
    "options": [
     "He was lifted up upon the cross and slain for the sins of the world",
     "He ascended into heaven in glory",
     "He was carried into Babylon",
     "He was hidden away by his apostles"
    ],
    "answer": 0
   },
   {
    "id": "1-ne-11-mp-36",
    "type": "match_pairs",
    "after_verse": 36,
    "pairs": [
     {
      "left": "Tree of life",
      "right": "The love of God"
     },
     {
      "left": "Rod of iron",
      "right": "The word of God"
     },
     {
      "left": "Great and spacious building",
      "right": "The pride of the world"
     },
     {
      "left": "The virgin of Nazareth",
      "right": "Mother of the Son of God"
     }
    ]
   }
  ],
  "12": [
   {
    "id": "1-ne-12-mc-2",
    "type": "multiple_choice",
    "after_verse": 2,
    "question": "What did Nephi see among his people through many generations?",
    "options": [
     "Wars, rumors of wars, and great slaughters with the sword",
     "Peace and prosperity without end",
     "A single mighty kingdom",
     "The building of many temples"
    ],
    "answer": 0
   },
   {
    "id": "1-ne-12-cur-4",
    "type": "curiosity",
    "after_verse": 4,
    "title": "Signs of destruction",
    "text": "Nephi foresaw earthquakes, fire, and a vapor of darkness that would sink and burn whole cities in the promised land - the very signs fulfilled at the Savior's death, recorded in 3 Nephi."
   },
   {
    "id": "1-ne-12-mc-6",
    "type": "multiple_choice",
    "after_verse": 6,
    "question": "After the destruction, whom did Nephi see descend from heaven and show himself to the survivors?",
    "options": [
     "The Lamb of God",
     "An army of angels",
     "Twelve apostles",
     "The prophet who prepares the way"
    ],
    "answer": 0
   },
   {
    "id": "1-ne-12-cur-8",
    "type": "curiosity",
    "after_verse": 8,
    "title": "Two sets of twelve",
    "text": "Nephi saw twelve disciples chosen to minister to his seed in the promised land, distinct from the twelve apostles at Jerusalem. The angel explained that the apostles would judge the house of Israel, and the twelve ministers would judge Nephi's seed."
   },
   {
    "id": "1-ne-12-fb-10",
    "type": "fill_blank",
    "after_verse": 10,
    "verse": 10,
    "template": "their garments are made white in his {0}",
    "blanks": [
     "blood"
    ],
    "distractors": [
     "name",
     "light",
     "mercy"
    ]
   },
   {
    "id": "1-ne-12-mc-11",
    "type": "multiple_choice",
    "after_verse": 11,
    "question": "What did Nephi behold pass away in righteousness, their garments white like the Lamb of God?",
    "options": [
     "Three generations",
     "Seven kings",
     "All the nations of the earth",
     "The twelve apostles"
    ],
    "answer": 0
   },
   {
    "id": "1-ne-12-mp-18",
    "type": "match_pairs",
    "after_verse": 18,
    "pairs": [
     {
      "left": "Fountain of filthy water",
      "right": "The depths of hell"
     },
     {
      "left": "Mists of darkness",
      "right": "The temptations of the devil"
     },
     {
      "left": "Great and spacious building",
      "right": "The pride of the children of men"
     },
     {
      "left": "The great gulf",
      "right": "The justice of the Eternal God"
     }
    ]
   },
   {
    "id": "1-ne-12-mc-19",
    "type": "multiple_choice",
    "after_verse": 19,
    "question": "Why did Nephi see the seed of his brethren overpower his own seed?",
    "options": [
     "Because of the pride of his seed and the temptations of the devil",
     "Because his seed had no weapons",
     "Because the Lord had abandoned them",
     "Because of famine in the land"
    ],
    "answer": 0
   },
   {
    "id": "1-ne-12-mc-22",
    "type": "multiple_choice",
    "after_verse": 22,
    "question": "What did the angel say would become of the seed of the brethren?",
    "options": [
     "They would dwindle in unbelief",
     "They would build a great temple",
     "They would all be saved",
     "They would return to Jerusalem"
    ],
    "answer": 0
   }
  ],
  "13": [
   {
    "id": "1-ne-13-mc-5",
    "type": "multiple_choice",
    "after_verse": 5,
    "question": "What did the angel call the church Nephi saw form among the Gentiles?",
    "options": [
     "Most abominable above all other churches",
     "The church of the Lamb of God",
     "The church of the saints",
     "A church of prophets"
    ],
    "answer": 0
   },
   {
    "id": "1-ne-13-cur-6",
    "type": "curiosity",
    "after_verse": 6,
    "title": "Founded by the devil",
    "text": "Nephi saw that the great and abominable church was founded by the devil himself. The angel later called it 'the mother of harlots' and 'the mother of abominations' - it stands for all that fights against the Lamb of God."
   },
   {
    "id": "1-ne-13-mc-8",
    "type": "multiple_choice",
    "after_verse": 8,
    "question": "What did the angel say the gold, silver, silks, and harlots represented?",
    "options": [
     "The desires of the great and abominable church",
     "The treasures of the temple",
     "The covenants of the Lord",
     "The gifts of the Gentiles"
    ],
    "answer": 0
   },
   {
    "id": "1-ne-13-mc-11",
    "type": "multiple_choice",
    "after_verse": 11,
    "question": "What did the angel say was upon the seed of Nephi's brethren?",
    "options": [
     "The wrath of God",
     "The blessing of the Lord",
     "The gift of prophecy",
     "The covenant of peace"
    ],
    "answer": 0
   },
   {
    "id": "1-ne-13-cur-12",
    "type": "curiosity",
    "after_verse": 12,
    "title": "A man across the waters",
    "text": "Nephi saw the Spirit of God move upon a man among the Gentiles who crossed the many waters to the promised land. Latter-day readers commonly understand this man to be Christopher Columbus."
   },
   {
    "id": "1-ne-13-mc-20",
    "type": "multiple_choice",
    "after_verse": 20,
    "question": "As the Gentiles prospered in the land, what did Nephi behold carried forth among them?",
    "options": [
     "A book",
     "A sword",
     "A temple",
     "A ship"
    ],
    "answer": 0
   },
   {
    "id": "1-ne-13-mc-23",
    "type": "multiple_choice",
    "after_verse": 23,
    "question": "What did the angel say the book proceeding from the mouth of a Jew was?",
    "options": [
     "A record of the Jews containing the covenants of the Lord",
     "A history of the Gentile kings",
     "The genealogy of Lehi",
     "A book of Egyptian learning"
    ],
    "answer": 0
   },
   {
    "id": "1-ne-13-fb-27",
    "type": "fill_blank",
    "after_verse": 27,
    "verse": 27,
    "template": "blind the eyes and {0} the hearts of the children of men",
    "blanks": [
     "harden"
    ],
    "distractors": [
     "soften",
     "gladden",
     "open"
    ]
   },
   {
    "id": "1-ne-13-mc-28",
    "type": "multiple_choice",
    "after_verse": 28,
    "question": "According to the angel, what happened to the book after it passed through the great and abominable church?",
    "options": [
     "Many plain and precious things were taken away from it",
     "It was burned entirely",
     "It was translated into Egyptian",
     "It was hidden in the temple"
    ],
    "answer": 0
   },
   {
    "id": "1-ne-13-mc-33",
    "type": "multiple_choice",
    "after_verse": 33,
    "question": "What did the Lamb of God promise concerning the Gentiles?",
    "options": [
     "I will be merciful unto the Gentiles",
     "I will destroy the Gentiles utterly",
     "The Gentiles shall never receive my gospel",
     "The Gentiles shall rule forever"
    ],
    "answer": 0
   },
   {
    "id": "1-ne-13-cur-35",
    "type": "curiosity",
    "after_verse": 35,
    "title": "The Book of Mormon foreseen",
    "text": "The Lamb promised that the things written by Nephi's seed would be hid up and come forth to the Gentiles 'by the gift and power of the Lamb' - a prophecy of the Book of Mormon, restoring plain and precious truths."
   },
   {
    "id": "1-ne-13-fb-37",
    "type": "fill_blank",
    "after_verse": 37,
    "verse": 37,
    "template": "how beautiful upon the {0} shall they be",
    "blanks": [
     "mountains"
    ],
    "distractors": [
     "hills",
     "valleys",
     "waters"
    ]
   },
   {
    "id": "1-ne-13-mc-40",
    "type": "multiple_choice",
    "after_verse": 40,
    "question": "What did the angel say the 'other books' coming forth would do?",
    "options": [
     "Establish the truth of the first records and restore the plain and precious things",
     "Replace the records of the apostles",
     "Reveal the genealogy of the Gentiles",
     "Record the wars of the Nephites"
    ],
    "answer": 0
   },
   {
    "id": "1-ne-13-mc-42",
    "type": "multiple_choice",
    "after_verse": 42,
    "question": "How did the angel say the Lord would manifest himself to the Jews and the Gentiles?",
    "options": [
     "To both, so that the last shall be first and the first shall be last",
     "Only to the Jews",
     "Only to the Gentiles",
     "To neither until the end of the world"
    ],
    "answer": 0
   }
  ],
  "14": [
   {
    "id": "1-ne-14-mc-2",
    "type": "multiple_choice",
    "after_verse": 2,
    "question": "What did the angel say of the Gentiles who hearken to the Lamb and harden not their hearts?",
    "options": [
     "They shall be numbered among the house of Israel and be a blessed people",
     "They shall be cast into captivity",
     "They shall lose the promised land",
     "They shall be made servants"
    ],
    "answer": 0
   },
   {
    "id": "1-ne-14-mc-10",
    "type": "multiple_choice",
    "after_verse": 10,
    "question": "How many churches did the angel say there are?",
    "options": [
     "Only two: the church of the Lamb of God and the church of the devil",
     "Three churches",
     "Seven churches",
     "Twelve churches"
    ],
    "answer": 0
   },
   {
    "id": "1-ne-14-mc-12",
    "type": "multiple_choice",
    "after_verse": 12,
    "question": "Why were the numbers of the church of the Lamb of God few?",
    "options": [
     "Because of the wickedness and abominations of the great whore",
     "Because they had no prophets",
     "Because they lived only in one land",
     "Because they refused to preach"
    ],
    "answer": 0
   },
   {
    "id": "1-ne-14-fb-14",
    "type": "fill_blank",
    "after_verse": 14,
    "verse": 14,
    "template": "they were armed with {0} and with the power of God",
    "blanks": [
     "righteousness"
    ],
    "distractors": [
     "faith",
     "wisdom",
     "mercy"
    ]
   },
   {
    "id": "1-ne-14-cur-17",
    "type": "curiosity",
    "after_verse": 17,
    "title": "The work of the Father",
    "text": "The angel foretold that when God's wrath is poured out on the mother of harlots, 'the work of the Father shall commence' - preparing the way to fulfill his covenants with the house of Israel."
   },
   {
    "id": "1-ne-14-mc-20",
    "type": "multiple_choice",
    "after_verse": 20,
    "question": "When the angel said 'Behold one of the twelve apostles of the Lamb,' what was the man wearing?",
    "options": [
     "A white robe",
     "Armor of gold",
     "A crown",
     "Priestly garments"
    ],
    "answer": 0
   },
   {
    "id": "1-ne-14-mc-22",
    "type": "multiple_choice",
    "after_verse": 22,
    "question": "Besides the remainder of Nephi's vision, what would this apostle also write about?",
    "options": [
     "The end of the world",
     "The wars of the Nephites",
     "The genealogy of the Jews",
     "The building of the temple"
    ],
    "answer": 0
   },
   {
    "id": "1-ne-14-cur-27",
    "type": "curiosity",
    "after_verse": 27,
    "title": "The apostle was John",
    "text": "The man in the white robe, ordained to write the remainder of the vision and the end of the world, was named John by the angel - the apostle John, author of the book of Revelation."
   },
   {
    "id": "1-ne-14-mp-27",
    "type": "match_pairs",
    "after_verse": 27,
    "pairs": [
     {
      "left": "Church of the Lamb of God",
      "right": "The saints of God"
     },
     {
      "left": "Mother of abominations",
      "right": "The church of the devil"
     },
     {
      "left": "The whore of all the earth",
      "right": "Sits upon many waters"
     },
     {
      "left": "John the apostle",
      "right": "Writes the remainder of the vision"
     }
    ]
   },
   {
    "id": "1-ne-14-mc-28",
    "type": "multiple_choice",
    "after_verse": 28,
    "question": "Why did Nephi write only a small part of the things he saw?",
    "options": [
     "He was forbidden; the Lord ordained the apostle John to write the rest",
     "He forgot most of the vision",
     "He ran out of plates",
     "The angel told him to write everything"
    ],
    "answer": 0
   }
  ],
  "15": [
   {
    "id": "1-ne-15-mc-2",
    "type": "multiple_choice",
    "after_verse": 2,
    "question": "What were Nephi's brethren doing when he returned to the tent?",
    "options": [
     "Disputing about the things their father had spoken",
     "Praying to the Lord",
     "Preparing to return to Jerusalem",
     "Building an altar"
    ],
    "answer": 0
   },
   {
    "id": "1-ne-15-mc-9",
    "type": "multiple_choice",
    "after_verse": 9,
    "question": "What had the brethren failed to do to understand their father's words?",
    "options": [
     "Inquire of the Lord",
     "Read the brass plates",
     "Fast for many days",
     "Ask their mother"
    ],
    "answer": 0
   },
   {
    "id": "1-ne-15-cur-11",
    "type": "curiosity",
    "after_verse": 11,
    "title": "Ask, and it shall be made known",
    "text": "Nephi reminded his brothers of the Lord's promise: if they would not harden their hearts, but ask in faith, believing they would receive, and keep the commandments with diligence, these things would be made known to them."
   },
   {
    "id": "1-ne-15-mc-12",
    "type": "multiple_choice",
    "after_verse": 12,
    "question": "To what was the house of Israel compared?",
    "options": [
     "An olive tree",
     "A flock of sheep",
     "A mighty river",
     "A high mountain"
    ],
    "answer": 0
   },
   {
    "id": "1-ne-15-mc-20",
    "type": "multiple_choice",
    "after_verse": 20,
    "question": "Whose words did Nephi rehearse concerning the restoration of the Jews?",
    "options": [
     "Isaiah",
     "Jeremiah",
     "Moses",
     "Abraham"
    ],
    "answer": 0
   },
   {
    "id": "1-ne-15-mc-22",
    "type": "multiple_choice",
    "after_verse": 22,
    "question": "What did Nephi say the tree his father saw represented?",
    "options": [
     "The tree of life",
     "The house of Israel",
     "The great and spacious building",
     "The river of water"
    ],
    "answer": 0
   },
   {
    "id": "1-ne-15-fb-24",
    "type": "fill_blank",
    "after_verse": 24,
    "verse": 24,
    "template": "it was the {0} of God",
    "blanks": [
     "word"
    ],
    "distractors": [
     "love",
     "law",
     "light"
    ]
   },
   {
    "id": "1-ne-15-mc-27",
    "type": "multiple_choice",
    "after_verse": 27,
    "question": "What did Nephi say the river of water his father saw was?",
    "options": [
     "Filthiness",
     "Living waters",
     "The love of God",
     "The word of God"
    ],
    "answer": 0
   },
   {
    "id": "1-ne-15-mp-30",
    "type": "match_pairs",
    "after_verse": 30,
    "pairs": [
     {
      "left": "Tree of life",
      "right": "The greatest gift of God"
     },
     {
      "left": "Rod of iron",
      "right": "The word of God"
     },
     {
      "left": "River of water",
      "right": "Filthiness"
     },
     {
      "left": "The awful gulf",
      "right": "Hell prepared for the wicked"
     }
    ]
   },
   {
    "id": "1-ne-15-mc-34",
    "type": "multiple_choice",
    "after_verse": 34,
    "question": "What did Nephi teach about the kingdom of God?",
    "options": [
     "No unclean thing can enter into it",
     "Only prophets may enter it",
     "It is found in Jerusalem",
     "It is filthy like the world"
    ],
    "answer": 0
   },
   {
    "id": "1-ne-15-mc-36",
    "type": "multiple_choice",
    "after_verse": 36,
    "question": "How did Nephi describe the fruit of the tree of life?",
    "options": [
     "The greatest of all the gifts of God",
     "A fruit forbidden to men",
     "Bitter to the taste",
     "Reserved only for the Jews"
    ],
    "answer": 0
   }
  ],
  "16": [
   {
    "id": "1-ne-16-mc-2",
    "type": "multiple_choice",
    "after_verse": 2,
    "question": "Why, according to Nephi, does the guilty take the truth to be hard?",
    "options": [
     "Because it cuts them to the very center",
     "Because it is spoken in anger",
     "Because it is written in a strange language",
     "Because it is too long"
    ],
    "answer": 0
   },
   {
    "id": "1-ne-16-mc-7",
    "type": "multiple_choice",
    "after_verse": 7,
    "question": "Whom did Nephi, his brethren, and Zoram take to wife?",
    "options": [
     "The daughters of Ishmael",
     "Women of the Gentiles",
     "Daughters of Laban",
     "Women of Bountiful"
    ],
    "answer": 0
   },
   {
    "id": "1-ne-16-cur-10",
    "type": "curiosity",
    "after_verse": 10,
    "title": "The Liahona",
    "text": "At the tent door Lehi found a round ball of fine brass with two spindles that pointed the way through the wilderness. Centuries later the prophet Alma called it the Liahona, meaning 'compass.'"
   },
   {
    "id": "1-ne-16-mc-13",
    "type": "multiple_choice",
    "after_verse": 13,
    "question": "What did they name the place where they pitched their tents after four days?",
    "options": [
     "Shazer",
     "Nahom",
     "Bountiful",
     "Jerusalem"
    ],
    "answer": 0
   },
   {
    "id": "1-ne-16-fb-18",
    "type": "fill_blank",
    "after_verse": 18,
    "verse": 18,
    "template": "which was made of fine {0}",
    "blanks": [
     "steel"
    ],
    "distractors": [
     "wood",
     "brass",
     "iron"
    ]
   },
   {
    "id": "1-ne-16-mc-23",
    "type": "multiple_choice",
    "after_verse": 23,
    "question": "After breaking his steel bow, what did Nephi do?",
    "options": [
     "Made a bow out of wood and an arrow from a straight stick",
     "Returned to Jerusalem for a new bow",
     "Gave up hunting",
     "Borrowed Laman's bow"
    ],
    "answer": 0
   },
   {
    "id": "1-ne-16-cur-28",
    "type": "curiosity",
    "after_verse": 28,
    "title": "Guided by faith",
    "text": "Nephi saw that the pointers in the ball worked according to the family's faith, diligence, and heed, and that a new writing appeared on it from time to time, giving them understanding concerning the ways of the Lord."
   },
   {
    "id": "1-ne-16-mc-29",
    "type": "multiple_choice",
    "after_verse": 29,
    "question": "What did Nephi learn from how the ball worked?",
    "options": [
     "By small means the Lord can bring about great things",
     "The ball worked only at night",
     "Only Lehi could read the ball",
     "The ball led them back to Jerusalem"
    ],
    "answer": 0
   },
   {
    "id": "1-ne-16-mc-34",
    "type": "multiple_choice",
    "after_verse": 34,
    "question": "Where was Ishmael buried?",
    "options": [
     "Nahom",
     "Shazer",
     "Bountiful",
     "The valley of Lemuel"
    ],
    "answer": 0
   },
   {
    "id": "1-ne-16-mc-37",
    "type": "multiple_choice",
    "after_verse": 37,
    "question": "What did Laman propose to Lemuel and the sons of Ishmael?",
    "options": [
     "To slay Lehi and Nephi",
     "To return to Bountiful",
     "To build a ship",
     "To worship the Lord"
    ],
    "answer": 0
   }
  ],
  "17": [
   {
    "id": "1-ne-17-mc-4",
    "type": "multiple_choice",
    "after_verse": 4,
    "question": "How long did the family sojourn in the wilderness?",
    "options": [
     "Eight years",
     "Forty years",
     "Three years",
     "Twelve years"
    ],
    "answer": 0
   },
   {
    "id": "1-ne-17-cur-5",
    "type": "curiosity",
    "after_verse": 5,
    "title": "Bountiful and Irreantum",
    "text": "After eight years the family reached a fruitful land by the sea, which they named Bountiful. They called the sea Irreantum, which Nephi says means 'many waters.'"
   },
   {
    "id": "1-ne-17-mc-8",
    "type": "multiple_choice",
    "after_verse": 8,
    "question": "What did the Lord command Nephi to build?",
    "options": [
     "A ship to carry his people across the waters",
     "A temple by the sea",
     "An altar of stones",
     "A new set of plates"
    ],
    "answer": 0
   },
   {
    "id": "1-ne-17-fb-13",
    "type": "fill_blank",
    "after_verse": 13,
    "verse": 13,
    "template": "I will also be your {0} in the wilderness",
    "blanks": [
     "light"
    ],
    "distractors": [
     "guide",
     "shield",
     "strength"
    ]
   },
   {
    "id": "1-ne-17-mc-17",
    "type": "multiple_choice",
    "after_verse": 17,
    "question": "How did the brothers react when Nephi began to build a ship?",
    "options": [
     "They murmured and called him a fool",
     "They eagerly helped him",
     "They prayed for guidance",
     "They asked to learn the craft"
    ],
    "answer": 0
   },
   {
    "id": "1-ne-17-mc-23",
    "type": "multiple_choice",
    "after_verse": 23,
    "question": "What example did Nephi use to answer his murmuring brothers?",
    "options": [
     "The children of Israel led out of Egypt",
     "The fall of Jerusalem",
     "The flood of Noah",
     "The tower of Babel"
    ],
    "answer": 0
   },
   {
    "id": "1-ne-17-mc-26",
    "type": "multiple_choice",
    "after_verse": 26,
    "question": "By Moses' word, what happened to the waters of the Red Sea?",
    "options": [
     "They were divided and Israel passed on dry ground",
     "They turned to blood",
     "They rose into a great storm",
     "They dried up forever"
    ],
    "answer": 0
   },
   {
    "id": "1-ne-17-mc-35",
    "type": "multiple_choice",
    "after_verse": 35,
    "question": "What did Nephi teach about how the Lord esteems all flesh?",
    "options": [
     "He esteemeth all flesh in one; the righteous is favored of God",
     "He favors only the house of Israel",
     "He esteems the rich above the poor",
     "He has rejected all the Gentiles"
    ],
    "answer": 0
   },
   {
    "id": "1-ne-17-mc-40",
    "type": "multiple_choice",
    "after_verse": 40,
    "question": "With which fathers did Nephi say the Lord made his covenant?",
    "options": [
     "Abraham, Isaac, and Jacob",
     "Adam, Seth, and Enoch",
     "Noah, Shem, and Japheth",
     "Saul, David, and Solomon"
    ],
    "answer": 0
   },
   {
    "id": "1-ne-17-fb-41",
    "type": "fill_blank",
    "after_verse": 41,
    "verse": 41,
    "template": "He sent fiery flying {0} among them",
    "blanks": [
     "serpents"
    ],
    "distractors": [
     "locusts",
     "hornets",
     "flies"
    ]
   },
   {
    "id": "1-ne-17-cur-45",
    "type": "curiosity",
    "after_verse": 45,
    "title": "A still small voice",
    "text": "Nephi told his brothers that the Lord had spoken to them in a still small voice, but they were past feeling and could not feel his words; so he spoke to them like the voice of thunder."
   },
   {
    "id": "1-ne-17-mc-48",
    "type": "multiple_choice",
    "after_verse": 48,
    "question": "When the brethren came to throw Nephi into the sea, what did he do?",
    "options": [
     "Filled with the power of God, he forbade them to touch him",
     "He leaped into the sea himself",
     "He called down fire from heaven",
     "He fled into the wilderness"
    ],
    "answer": 0
   },
   {
    "id": "1-ne-17-mc-55",
    "type": "multiple_choice",
    "after_verse": 55,
    "question": "After the Lord shook the brethren, what did they try to do to Nephi?",
    "options": [
     "Worship him, but he would not allow it",
     "Bind him again with cords",
     "Throw him into the sea",
     "Crown him as king"
    ],
    "answer": 0
   }
  ],
  "18": [
   {
    "id": "1-ne-18-mc-2",
    "type": "multiple_choice",
    "after_verse": 2,
    "question": "How did Nephi build the ship?",
    "options": [
     "After the manner the Lord showed him, not after the manner of men",
     "Copying the ships of the Egyptians",
     "With the help of skilled shipbuilders",
     "Out of reeds and pitch"
    ],
    "answer": 0
   },
   {
    "id": "1-ne-18-cur-7",
    "type": "curiosity",
    "after_verse": 7,
    "title": "Jacob and Joseph",
    "text": "Two more sons were born to Lehi and Sariah during the eight years in the wilderness: Jacob and Joseph. Jacob would later become a prophet and write his own book in the Book of Mormon."
   },
   {
    "id": "1-ne-18-mc-9",
    "type": "multiple_choice",
    "after_verse": 9,
    "question": "How did the brethren and the sons of Ishmael behave on the voyage?",
    "options": [
     "They made merry, danced, and spoke with much rudeness, forgetting the Lord",
     "They prayed and gave thanks continually",
     "They studied the brass plates",
     "They kept silent in fear"
    ],
    "answer": 0
   },
   {
    "id": "1-ne-18-mc-11",
    "type": "multiple_choice",
    "after_verse": 11,
    "question": "What did Laman and Lemuel do to Nephi on the ship?",
    "options": [
     "Bound him with cords and treated him harshly",
     "Threw him into the sea",
     "Made him the captain",
     "Left him at Bountiful"
    ],
    "answer": 0
   },
   {
    "id": "1-ne-18-fb-12",
    "type": "fill_blank",
    "after_verse": 12,
    "verse": 12,
    "template": "the {0}, which had been prepared of the Lord, did cease to work",
    "blanks": [
     "compass"
    ],
    "distractors": [
     "rudder",
     "anchor",
     "sail"
    ]
   },
   {
    "id": "1-ne-18-cur-17",
    "type": "curiosity",
    "after_verse": 17,
    "title": "Lehi and Sariah brought low",
    "text": "The harshness of Laman and Lemuel during the storm brought the aged Lehi and Sariah near to death upon their sick-beds; even the tears of Nephi's wife and children could not soften his brothers."
   },
   {
    "id": "1-ne-18-mc-20",
    "type": "multiple_choice",
    "after_verse": 20,
    "question": "What finally softened the brothers' hearts to loose Nephi?",
    "options": [
     "The power of God, when they were about to be swallowed up in the sea",
     "The tears of Nephi's wife",
     "The counsel of Lehi",
     "A promise of gold"
    ],
    "answer": 0
   },
   {
    "id": "1-ne-18-mc-21",
    "type": "multiple_choice",
    "after_verse": 21,
    "question": "After the brothers loosed Nephi and he prayed, what happened?",
    "options": [
     "The winds and the storm ceased, and there was a great calm",
     "The ship sank",
     "They returned to Bountiful",
     "A new storm arose"
    ],
    "answer": 0
   },
   {
    "id": "1-ne-18-mc-25",
    "type": "multiple_choice",
    "after_verse": 25,
    "question": "What did they find on the land of promise?",
    "options": [
     "Beasts of every kind and ore of gold, silver, and copper",
     "Great cities already built",
     "A people who spoke their language",
     "Ships of other nations"
    ],
    "answer": 0
   }
  ],
  "19": [
   {
    "id": "1-ne-19-mc-3",
    "type": "multiple_choice",
    "after_verse": 3,
    "question": "What was Nephi commanded to write upon these plates?",
    "options": [
     "The ministry and the prophecies, the more plain and precious parts",
     "The wars and contentions of his people",
     "The genealogy of his fathers",
     "The reign of the kings"
    ],
    "answer": 0
   },
   {
    "id": "1-ne-19-mc-8",
    "type": "multiple_choice",
    "after_verse": 8,
    "question": "How long after Lehi left Jerusalem did the angel say the Messiah would come?",
    "options": [
     "Six hundred years",
     "Forty years",
     "A thousand years",
     "Three hundred years"
    ],
    "answer": 0
   },
   {
    "id": "1-ne-19-mp-10",
    "type": "match_pairs",
    "after_verse": 10,
    "pairs": [
     {
      "left": "Zenock",
      "right": "Christ would be lifted up"
     },
     {
      "left": "Neum",
      "right": "Christ would be crucified"
     },
     {
      "left": "Zenos",
      "right": "Christ would be buried; three days of darkness"
     }
    ]
   },
   {
    "id": "1-ne-19-mc-13",
    "type": "multiple_choice",
    "after_verse": 13,
    "question": "According to the prophet, why would those at Jerusalem be scourged by all people?",
    "options": [
     "Because they crucify the God of Israel",
     "Because they kept the law of Moses",
     "Because they built the temple",
     "Because they gathered Israel"
    ],
    "answer": 0
   },
   {
    "id": "1-ne-19-cur-14",
    "type": "curiosity",
    "after_verse": 14,
    "title": "A hiss and a byword",
    "text": "The prophet foretold that the Jews, for turning their hearts from the Holy One of Israel, would wander, be hated, and become 'a hiss and a byword' among all nations - a prophecy of the long scattering of the Jews."
   },
   {
    "id": "1-ne-19-mc-16",
    "type": "multiple_choice",
    "after_verse": 16,
    "question": "What did the Lord promise to do for the house of Israel in the last days?",
    "options": [
     "Gather them in from the four quarters of the earth",
     "Destroy them utterly",
     "Leave them scattered forever",
     "Make them rulers over the Gentiles"
    ],
    "answer": 0
   },
   {
    "id": "1-ne-19-fb-23",
    "type": "fill_blank",
    "after_verse": 23,
    "verse": 23,
    "template": "that it might be for our {0} and learning",
    "blanks": [
     "profit"
    ],
    "distractors": [
     "joy",
     "comfort",
     "salvation"
    ]
   },
   {
    "id": "1-ne-19-cur-23",
    "type": "curiosity",
    "after_verse": 23,
    "title": "Liken the scriptures",
    "text": "Nephi read to his brothers from the books of Moses and from Isaiah, and said he 'did liken all scriptures' unto his people - reading them as if written for their own profit and learning."
   },
   {
    "id": "1-ne-19-mc-24",
    "type": "multiple_choice",
    "after_verse": 24,
    "question": "How did Nephi address his people as he taught them the words of the prophets?",
    "options": [
     "As a remnant of the house of Israel, a branch broken off",
     "As the children of the Gentiles",
     "As strangers to the covenant",
     "As the people of Babylon"
    ],
    "answer": 0
   }
  ],
  "20": [
   {
    "id": "1-ne-20-cur-1",
    "type": "curiosity",
    "after_verse": 1,
    "title": "Isaiah, quoted in the New World",
    "text": "First Nephi 20 is Isaiah chapter 48. Nephi read it from the brass plates; the Book of Mormon version adds the phrase 'or out of the waters of baptism,' a clarification not found in the Bible."
   },
   {
    "id": "1-ne-20-mc-5",
    "type": "multiple_choice",
    "after_verse": 5,
    "question": "Why did the Lord declare these things before they came to pass?",
    "options": [
     "Lest Israel should credit their idols and graven images",
     "To frighten the Chaldeans",
     "To reward the prophets",
     "Because Babylon had repented"
    ],
    "answer": 0
   },
   {
    "id": "1-ne-20-fb-10",
    "type": "fill_blank",
    "after_verse": 10,
    "verse": 10,
    "template": "I have chosen thee in the furnace of {0}",
    "blanks": [
     "affliction"
    ],
    "distractors": [
     "bondage",
     "judgment",
     "exile"
    ]
   },
   {
    "id": "1-ne-20-mc-12",
    "type": "multiple_choice",
    "after_verse": 12,
    "question": "What did the Lord declare about himself to Jacob and Israel?",
    "options": [
     "I am the first, and I am also the last",
     "I am only the God of Jerusalem",
     "I am one among many gods",
     "I dwell only in the temple"
    ],
    "answer": 0
   },
   {
    "id": "1-ne-20-fb-18",
    "type": "fill_blank",
    "after_verse": 18,
    "verse": 18,
    "template": "then had thy {0} been as a river",
    "blanks": [
     "peace"
    ],
    "distractors": [
     "joy",
     "hope",
     "glory"
    ]
   },
   {
    "id": "1-ne-20-mc-20",
    "type": "multiple_choice",
    "after_verse": 20,
    "question": "What did Isaiah command concerning Babylon?",
    "options": [
     "Go ye forth of Babylon, flee from the Chaldeans",
     "Build a temple in Babylon",
     "Make peace with the Chaldeans",
     "Remain in Babylon forever"
    ],
    "answer": 0
   },
   {
    "id": "1-ne-20-mc-22",
    "type": "multiple_choice",
    "after_verse": 22,
    "question": "What did the Lord say there is for the wicked?",
    "options": [
     "There is no peace",
     "There is endless wealth",
     "There is a sure refuge",
     "There is great honor"
    ],
    "answer": 0
   }
  ],
  "21": [
   {
    "id": "1-ne-21-cur-1",
    "type": "curiosity",
    "after_verse": 1,
    "title": "Isaiah 49 and the isles of the sea",
    "text": "First Nephi 21 is Isaiah 49. Nephi applied Isaiah's words about scattered Israel and the 'isles of the sea' to his own family, who had crossed the ocean to a far land."
   },
   {
    "id": "1-ne-21-mc-3",
    "type": "multiple_choice",
    "after_verse": 3,
    "question": "Whom did the Lord call his servant, in whom he would be glorified?",
    "options": [
     "Israel",
     "Babylon",
     "Egypt",
     "The Chaldeans"
    ],
    "answer": 0
   },
   {
    "id": "1-ne-21-fb-6",
    "type": "fill_blank",
    "after_verse": 6,
    "verse": 6,
    "template": "give thee for a {0} to the Gentiles",
    "blanks": [
     "light"
    ],
    "distractors": [
     "sign",
     "guide",
     "witness"
    ]
   },
   {
    "id": "1-ne-21-mc-12",
    "type": "multiple_choice",
    "after_verse": 12,
    "question": "From what directions and land did Isaiah say Israel would be gathered?",
    "options": [
     "From the north, the west, and the land of Sinim",
     "From Babylon and Egypt only",
     "From Jerusalem alone",
     "From the south and the east only"
    ],
    "answer": 0
   },
   {
    "id": "1-ne-21-cur-15",
    "type": "curiosity",
    "after_verse": 15,
    "title": "He will not forget Israel",
    "text": "Isaiah compared the Lord's love to a mother's: even if a woman could forget her nursing child, the Lord would never forget his people - he has graven them upon the palms of his hands."
   },
   {
    "id": "1-ne-21-mc-16",
    "type": "multiple_choice",
    "after_verse": 16,
    "question": "What did the Lord say he had done so as not to forget Zion?",
    "options": [
     "Graven her upon the palms of his hands",
     "Written her name in the sand",
     "Built her a great tower",
     "Sent her into Babylon"
    ],
    "answer": 0
   },
   {
    "id": "1-ne-21-mc-23",
    "type": "multiple_choice",
    "after_verse": 23,
    "question": "What did Isaiah say kings and queens would do for Israel?",
    "options": [
     "Care for them as nursing fathers and mothers",
     "Conquer and oppress them",
     "Judge and accuse them",
     "Drive them into exile"
    ],
    "answer": 0
   },
   {
    "id": "1-ne-21-mc-26",
    "type": "multiple_choice",
    "after_verse": 26,
    "question": "By what titles does the Lord close, that all flesh shall know him?",
    "options": [
     "Thy Savior and Redeemer, the Mighty One of Jacob",
     "The God of Babylon",
     "The Lord of the Chaldeans",
     "A prophet like Moses"
    ],
    "answer": 0
   }
  ],
  "22": [
   {
    "id": "1-ne-22-mc-3",
    "type": "multiple_choice",
    "after_verse": 3,
    "question": "Did Nephi say Isaiah's words pertained to spiritual or temporal things?",
    "options": [
     "To things both temporal and spiritual",
     "To spiritual things only",
     "To temporal things only",
     "To neither"
    ],
    "answer": 0
   },
   {
    "id": "1-ne-22-cur-4",
    "type": "curiosity",
    "after_verse": 4,
    "title": "The lost tribes",
    "text": "Nephi taught that the more part of the tribes of Israel had already been led away and scattered upon the isles of the sea, lost from the knowledge of those at Jerusalem - none knew where they had gone."
   },
   {
    "id": "1-ne-22-mc-7",
    "type": "multiple_choice",
    "after_verse": 7,
    "question": "What did Nephi say the Lord would raise up among the Gentiles upon this land?",
    "options": [
     "A mighty nation",
     "A new temple",
     "A line of kings",
     "A great famine"
    ],
    "answer": 0
   },
   {
    "id": "1-ne-22-fb-9",
    "type": "fill_blank",
    "after_verse": 9,
    "verse": 9,
    "template": "all the kindreds of the earth be {0}",
    "blanks": [
     "blessed"
    ],
    "distractors": [
     "gathered",
     "redeemed",
     "saved"
    ]
   },
   {
    "id": "1-ne-22-mc-12",
    "type": "multiple_choice",
    "after_verse": 12,
    "question": "What did Nephi say the Lord would do for scattered Israel?",
    "options": [
     "Bring them out of obscurity and darkness, and they shall know their Redeemer",
     "Leave them lost forever",
     "Make them rulers over the Gentiles",
     "Destroy them with the wicked"
    ],
    "answer": 0
   },
   {
    "id": "1-ne-22-cur-14",
    "type": "curiosity",
    "after_verse": 14,
    "title": "The great whore shall fall",
    "text": "Nephi declared that the great and abominable church - the whore of all the earth - would war within itself and tumble to the dust; all who fight against Zion shall be destroyed."
   },
   {
    "id": "1-ne-22-mc-20",
    "type": "multiple_choice",
    "after_verse": 20,
    "question": "What words of Moses did Nephi cite about a future prophet?",
    "options": [
     "A prophet shall the Lord raise up unto you, like unto me",
     "No prophet shall ever come again",
     "The law of Moses shall never change",
     "A king shall rule over Israel forever"
    ],
    "answer": 0
   },
   {
    "id": "1-ne-22-mc-21",
    "type": "multiple_choice",
    "after_verse": 21,
    "question": "Who did Nephi say was the prophet like Moses of whom Moses spoke?",
    "options": [
     "The Holy One of Israel",
     "Isaiah",
     "John the Baptist",
     "Lehi"
    ],
    "answer": 0
   },
   {
    "id": "1-ne-22-fb-25",
    "type": "fill_blank",
    "after_verse": 25,
    "verse": 25,
    "template": "there shall be one fold and one {0}",
    "blanks": [
     "shepherd"
    ],
    "distractors": [
     "king",
     "master",
     "father"
    ]
   },
   {
    "id": "1-ne-22-cur-26",
    "type": "curiosity",
    "after_verse": 26,
    "title": "Satan bound",
    "text": "Nephi foresaw a day when, because of the righteousness of the Lord's people, Satan would have no power over their hearts and could not be loosed for many years - the millennial reign of the Holy One of Israel."
   },
   {
    "id": "1-ne-22-mc-28",
    "type": "multiple_choice",
    "after_verse": 28,
    "question": "What did Nephi say all nations must do to dwell safely in the Holy One of Israel?",
    "options": [
     "Repent",
     "Pay tribute",
     "Gather to Jerusalem",
     "Build temples"
    ],
    "answer": 0
   },
   {
    "id": "1-ne-22-mp-28",
    "type": "match_pairs",
    "after_verse": 28,
    "pairs": [
     {
      "left": "The righteous",
      "right": "Preserved, even as by fire"
     },
     {
      "left": "The proud and the wicked",
      "right": "Burned as stubble"
     },
     {
      "left": "Those who fight against Zion",
      "right": "Shall be cut off"
     },
     {
      "left": "Nations that repent",
      "right": "Dwell safely in the Holy One of Israel"
     }
    ]
   },
   {
    "id": "1-ne-22-mc-31",
    "type": "multiple_choice",
    "after_verse": 31,
    "question": "How did Nephi say his people would be saved at the last day?",
    "options": [
     "By being obedient to the commandments and enduring to the end",
     "By keeping the law of Moses alone",
     "By trusting in Lehi's family only",
     "By gathering riches"
    ],
    "answer": 0
   }
  ]
 }
}