{
 "schema_version": 1,
 "book": "1-kgs",
 "chapters": {
  "1": [
   {
    "id": "1-kgs-1-cur-39",
    "type": "curiosity",
    "after_verse": 39,
    "title": "'God save king Solomon!'",
    "text": "Solomon was anointed with the oil from the tabernacle, to the sound of the trumpet, and the people shouted: 'God save king Solomon!' — confirming David's succession."
   },
   {
    "id": "1-kgs-1-mc-3",
    "type": "multiple_choice",
    "after_verse": 3,
    "question": "How is David described at the start of 1 Kings?",
    "options": [
     "Old and failing in strength",
     "Young and vigorous",
     "In the midst of war",
     "Newly crowned"
    ],
    "answer": 0
   },
   {
    "id": "1-kgs-1-mc-8",
    "type": "multiple_choice",
    "after_verse": 8,
    "question": "Who exalted himself, declaring himself king without his father's knowledge?",
    "options": [
     "Adonijah, David's son",
     "Solomon",
     "Joab",
     "Absalom"
    ],
    "answer": 0
   },
   {
    "id": "1-kgs-1-mc-14",
    "type": "multiple_choice",
    "after_verse": 14,
    "question": "Who warned David of Adonijah's attempt to seize the throne?",
    "options": [
     "The prophet Nathan and Bath-sheba",
     "Joab",
     "Zadok",
     "Shimei"
    ],
    "answer": 0
   },
   {
    "id": "1-kgs-1-mc-19",
    "type": "multiple_choice",
    "after_verse": 19,
    "question": "What had David sworn to Bath-sheba about the successor?",
    "options": [
     "That Solomon would reign after him",
     "That Adonijah would be king",
     "That he would divide the kingdom",
     "That there would be no king"
    ],
    "answer": 0
   },
   {
    "id": "1-kgs-1-mc-25",
    "type": "multiple_choice",
    "after_verse": 25,
    "question": "Whom did David have anointed king in his place?",
    "options": [
     "Solomon",
     "Adonijah",
     "Nathan",
     "Benaiah"
    ],
    "answer": 0
   },
   {
    "id": "1-kgs-1-mc-30",
    "type": "multiple_choice",
    "after_verse": 30,
    "question": "Where was Solomon anointed king?",
    "options": [
     "At Gihon, by Zadok and Nathan",
     "In the temple",
     "In Hebron",
     "In Gibeon"
    ],
    "answer": 0
   },
   {
    "id": "1-kgs-1-mc-35",
    "type": "multiple_choice",
    "after_verse": 35,
    "question": "How did the people react to Solomon's anointing?",
    "options": [
     "They rejoiced with great celebration",
     "They rebelled",
     "They were indifferent",
     "They fled"
    ],
    "answer": 0
   },
   {
    "id": "1-kgs-1-mc-40",
    "type": "multiple_choice",
    "after_verse": 40,
    "question": "What happened to Adonijah's guests when they heard about Solomon?",
    "options": [
     "They were afraid and scattered",
     "They attacked Solomon",
     "They crowned Adonijah",
     "They feasted"
    ],
    "answer": 0
   },
   {
    "id": "1-kgs-1-mc-44",
    "type": "multiple_choice",
    "after_verse": 44,
    "question": "What did Adonijah do in fear of Solomon?",
    "options": [
     "He caught hold of the horns of the altar",
     "He fled to Egypt",
     "He raised an army",
     "He begged David's pardon"
    ],
    "answer": 0
   },
   {
    "id": "1-kgs-1-mc-48",
    "type": "multiple_choice",
    "after_verse": 48,
    "question": "What did Solomon do with Adonijah at that moment?",
    "options": [
     "He spared him, on condition he be faithful",
     "He had him killed at once",
     "He crowned him co-king",
     "He exiled him"
    ],
    "answer": 0
   },
   {
    "id": "1-kgs-1-mc-51",
    "type": "multiple_choice",
    "after_verse": 51,
    "question": "What did Solomon say to Adonijah in sparing him?",
    "options": [
     "To go home, if he would show himself a worthy man",
     "Never to return",
     "That he would rule with him",
     "To choose exile"
    ],
    "answer": 0
   }
  ],
  "2": [
   {
    "id": "1-kgs-2-cur-2",
    "type": "curiosity",
    "after_verse": 2,
    "title": "David's last charge",
    "text": "Before dying, David charged Solomon: 'be thou strong, and show thyself a man; keep the charge of the Lord' — leaving him a spiritual legacy, not just a political one."
   },
   {
    "id": "1-kgs-2-mc-3",
    "type": "multiple_choice",
    "after_verse": 3,
    "question": "What central charge did David give Solomon before dying?",
    "options": [
     "To keep the commandments of the Lord and be strong",
     "To conquer Egypt",
     "To build a palace",
     "To raise taxes"
    ],
    "answer": 0
   },
   {
    "id": "1-kgs-2-mc-8",
    "type": "multiple_choice",
    "after_verse": 8,
    "question": "What did David charge Solomon concerning Joab and Shimei?",
    "options": [
     "To deal justly with them",
     "To reward them",
     "To exile them",
     "To forget them"
    ],
    "answer": 0
   },
   {
    "id": "1-kgs-2-mc-13",
    "type": "multiple_choice",
    "after_verse": 13,
    "question": "How did David end his days?",
    "options": [
     "He died in peace and was buried in the city of David",
     "He died in war",
     "He was deposed",
     "He abdicated"
    ],
    "answer": 0
   },
   {
    "id": "1-kgs-2-mc-18",
    "type": "multiple_choice",
    "after_verse": 18,
    "question": "What did Adonijah ask for, which cost him his life?",
    "options": [
     "Abishag, David's servant, as wife",
     "Half the kingdom",
     "Command of the army",
     "The priesthood"
    ],
    "answer": 0
   },
   {
    "id": "1-kgs-2-mc-22",
    "type": "multiple_choice",
    "after_verse": 22,
    "question": "What did Solomon do to Adonijah over that request?",
    "options": [
     "He had him killed, seeing in it a threat to the throne",
     "He pardoned him",
     "He crowned him",
     "He exiled him"
    ],
    "answer": 0
   },
   {
    "id": "1-kgs-2-mc-26",
    "type": "multiple_choice",
    "after_verse": 26,
    "question": "What did Solomon do to the priest Abiathar?",
    "options": [
     "He deposed him and banished him to Anathoth",
     "He killed him",
     "He promoted him",
     "He ignored him"
    ],
    "answer": 0
   },
   {
    "id": "1-kgs-2-mc-30",
    "type": "multiple_choice",
    "after_verse": 30,
    "question": "How did Joab die?",
    "options": [
     "He was killed by the altar, by Solomon's order",
     "In battle",
     "Of old age",
     "In exile"
    ],
    "answer": 0
   },
   {
    "id": "1-kgs-2-mc-34",
    "type": "multiple_choice",
    "after_verse": 34,
    "question": "Who replaced Joab over the army?",
    "options": [
     "Benaiah",
     "Abiathar",
     "Zadok",
     "Adonijah"
    ],
    "answer": 0
   },
   {
    "id": "1-kgs-2-mc-40",
    "type": "multiple_choice",
    "after_verse": 40,
    "question": "What condition did Solomon impose on Shimei?",
    "options": [
     "That he not leave Jerusalem, on pain of death",
     "That he pay tribute",
     "That he serve in the temple",
     "That he go into exile"
    ],
    "answer": 0
   },
   {
    "id": "1-kgs-2-mc-44",
    "type": "multiple_choice",
    "after_verse": 44,
    "question": "What happened to Shimei when he disobeyed and left Jerusalem?",
    "options": [
     "He was executed",
     "He was pardoned",
     "He was promoted",
     "He was exiled"
    ],
    "answer": 0
   }
  ],
  "3": [
   {
    "id": "1-kgs-3-cur-9",
    "type": "curiosity",
    "after_verse": 9,
    "title": "The request that pleased God",
    "text": "Solomon could have asked for riches or long life, but he asked for 'an understanding heart to judge the people' — so God gave him also what he did not ask."
   },
   {
    "id": "1-kgs-3-mc-3",
    "type": "multiple_choice",
    "after_verse": 3,
    "question": "How did Solomon's reign begin in his relationship with God?",
    "options": [
     "He loved the Lord, but still sacrificed in the high places",
     "He worshiped idols",
     "He rejected the temple",
     "He ignored the Law"
    ],
    "answer": 0
   },
   {
    "id": "1-kgs-3-mc-8",
    "type": "multiple_choice",
    "after_verse": 8,
    "question": "What did God offer Solomon in a dream at Gibeon?",
    "options": [
     "To ask whatever he wished",
     "An army",
     "Eternal life",
     "A sign in the sky"
    ],
    "answer": 0
   },
   {
    "id": "1-kgs-3-mc-13",
    "type": "multiple_choice",
    "after_verse": 13,
    "question": "What did Solomon ask of God?",
    "options": [
     "Wisdom to govern and discern good and evil",
     "Gold",
     "Long life",
     "Victory over enemies"
    ],
    "answer": 0
   },
   {
    "id": "1-kgs-3-mc-19",
    "type": "multiple_choice",
    "after_verse": 19,
    "question": "What did God give Solomon, besides what he asked?",
    "options": [
     "Also riches and honor",
     "A son",
     "A finished temple",
     "Rule over Egypt"
    ],
    "answer": 0
   },
   {
    "id": "1-kgs-3-mc-25",
    "type": "multiple_choice",
    "after_verse": 25,
    "question": "How did Solomon reveal his wisdom in the case of the two women?",
    "options": [
     "He proposed dividing the baby, revealing the true mother",
     "He cast lots",
     "He consulted a prophet",
     "He arrested them both"
    ],
    "answer": 0
   }
  ],
  "4": [
   {
    "id": "1-kgs-4-cur-25",
    "type": "curiosity",
    "after_verse": 25,
    "title": "'Every man under his vine'",
    "text": "At the height of Solomon's peace, it was said every Israelite lived secure 'under his vine and under his fig tree' — a biblical image of prosperity and peace."
   },
   {
    "id": "1-kgs-4-mc-3",
    "type": "multiple_choice",
    "after_verse": 3,
    "question": "What does chapter 4 list at the start?",
    "options": [
     "Solomon's chief officials",
     "The rebel tribes",
     "David's wars",
     "The temple laws"
    ],
    "answer": 0
   },
   {
    "id": "1-kgs-4-mc-8",
    "type": "multiple_choice",
    "after_verse": 8,
    "question": "How did Solomon arrange provision for the court?",
    "options": [
     "Twelve deputies, each providing one month a year",
     "By taxing the Philistines",
     "By importing from Egypt",
     "With a single treasurer"
    ],
    "answer": 0
   },
   {
    "id": "1-kgs-4-mc-13",
    "type": "multiple_choice",
    "after_verse": 13,
    "question": "What was life like in Judah and Israel under Solomon?",
    "options": [
     "Prosperous and secure, 'every man under his vine'",
     "In constant war",
     "Under famine",
     "In exile"
    ],
    "answer": 0
   },
   {
    "id": "1-kgs-4-mc-18",
    "type": "multiple_choice",
    "after_verse": 18,
    "question": "What gift marked Solomon's reign?",
    "options": [
     "An immense wisdom, given by God",
     "Military strength",
     "Inherited wealth",
     "An alliance with Egypt"
    ],
    "answer": 0
   },
   {
    "id": "1-kgs-4-mc-23",
    "type": "multiple_choice",
    "after_verse": 23,
    "question": "How does the Bible measure Solomon's wisdom?",
    "options": [
     "Greater than that of all the wise men of the East",
     "Equal to David's",
     "Limited to the court",
     "Only in proverbs"
    ],
    "answer": 0
   },
   {
    "id": "1-kgs-4-mc-28",
    "type": "multiple_choice",
    "after_verse": 28,
    "question": "What did Solomon produce, showing his wisdom?",
    "options": [
     "Thousands of proverbs and songs",
     "A military empire",
     "A new religion",
     "A law code"
    ],
    "answer": 0
   },
   {
    "id": "1-kgs-4-mc-32",
    "type": "multiple_choice",
    "after_verse": 32,
    "question": "Who came to hear Solomon's wisdom?",
    "options": [
     "People of all nations and kings of the earth",
     "Only the Israelites",
     "Only priests",
     "No one"
    ],
    "answer": 0
   }
  ],
  "5": [
   {
    "id": "1-kgs-5-cur-4",
    "type": "curiosity",
    "after_verse": 4,
    "title": "Why it fell to Solomon",
    "text": "David could not build the temple, having shed much blood in war; in a time of peace, it fell to his son Solomon to raise the house of the Lord."
   },
   {
    "id": "1-kgs-5-mc-3",
    "type": "multiple_choice",
    "after_verse": 3,
    "question": "With whom did Solomon make an alliance to obtain timber for the temple?",
    "options": [
     "Hiram, king of Tyre",
     "Pharaoh of Egypt",
     "The king of Syria",
     "The Philistines"
    ],
    "answer": 0
   },
   {
    "id": "1-kgs-5-mc-8",
    "type": "multiple_choice",
    "after_verse": 8,
    "question": "What did Hiram supply for building the temple?",
    "options": [
     "Cedars and cypress from Lebanon",
     "Gold from Egypt",
     "Stones from Arabia",
     "Soldiers"
    ],
    "answer": 0
   },
   {
    "id": "1-kgs-5-mc-13",
    "type": "multiple_choice",
    "after_verse": 13,
    "question": "What did Solomon give Hiram in exchange for the timber?",
    "options": [
     "Wheat and oil for his household",
     "Half of Jerusalem",
     "Gold from the temple",
     "Slaves"
    ],
    "answer": 0
   },
   {
    "id": "1-kgs-5-mc-16",
    "type": "multiple_choice",
    "after_verse": 16,
    "question": "How did Solomon gather a workforce for the great work?",
    "options": [
     "He levied thousands of laborers",
     "He hired Egyptians",
     "He used only the royal family",
     "He waited for volunteers"
    ],
    "answer": 0
   }
  ],
  "6": [
   {
    "id": "1-kgs-6-cur-7",
    "type": "curiosity",
    "after_verse": 7,
    "title": "A temple raised in silence",
    "text": "No sound of hammer, axe or tool was heard at the temple during construction: the stones were prepared offsite — a sign of reverence in raising the house of God."
   },
   {
    "id": "1-kgs-6-mc-3",
    "type": "multiple_choice",
    "after_verse": 3,
    "question": "When did Solomon begin to build the temple?",
    "options": [
     "In the fourth year of his reign",
     "In the first year",
     "After twenty years",
     "At the end of his life"
    ],
    "answer": 0
   },
   {
    "id": "1-kgs-6-mc-8",
    "type": "multiple_choice",
    "after_verse": 8,
    "question": "What was notable about the stones during construction?",
    "options": [
     "They were prepared offsite; no hammer was heard at the temple",
     "They were solid gold",
     "They came from Egypt",
     "They were cut on-site with great noise"
    ],
    "answer": 0
   },
   {
    "id": "1-kgs-6-mc-12",
    "type": "multiple_choice",
    "after_verse": 12,
    "question": "What promise did God make Solomon about the temple?",
    "options": [
     "He would dwell with Israel if he kept His commandments",
     "That it would last forever unconditionally",
     "That He would double his riches",
     "That no one would attack it"
    ],
    "answer": 0
   },
   {
    "id": "1-kgs-6-mc-17",
    "type": "multiple_choice",
    "after_verse": 17,
    "question": "With what was the interior of the temple lined?",
    "options": [
     "Cedar and gold",
     "Silver and bronze",
     "Marble",
     "Cloth"
    ],
    "answer": 0
   },
   {
    "id": "1-kgs-6-mc-23",
    "type": "multiple_choice",
    "after_verse": 23,
    "question": "What was in the inner sanctuary (the Holy of Holies)?",
    "options": [
     "Two wooden cherubim overlaid with gold",
     "A throne",
     "A fountain",
     "Twelve altars"
    ],
    "answer": 0
   },
   {
    "id": "1-kgs-6-mc-28",
    "type": "multiple_choice",
    "after_verse": 28,
    "question": "What were the temple's walls and doors like?",
    "options": [
     "Carved with cherubim, palm trees and flowers, and overlaid with gold",
     "Plain and white",
     "Of glass",
     "Undecorated"
    ],
    "answer": 0
   },
   {
    "id": "1-kgs-6-mc-34",
    "type": "multiple_choice",
    "after_verse": 34,
    "question": "How long did building the temple take?",
    "options": [
     "Seven years",
     "Forty years",
     "One year",
     "Twenty years"
    ],
    "answer": 0
   }
  ],
  "7": [
   {
    "id": "1-kgs-7-cur-21",
    "type": "curiosity",
    "after_verse": 21,
    "title": "Jachin and Boaz",
    "text": "The two bronze pillars of the porch had meaningful names: Jachin ('he establishes') and Boaz ('in him is strength') — a reminder that the house rested on God."
   },
   {
    "id": "1-kgs-7-mc-3",
    "type": "multiple_choice",
    "after_verse": 3,
    "question": "What did Solomon build, besides the temple?",
    "options": [
     "His own palace, over thirteen years",
     "A wall around Israel",
     "A fleet of ships",
     "A second city"
    ],
    "answer": 0
   },
   {
    "id": "1-kgs-7-mc-8",
    "type": "multiple_choice",
    "after_verse": 8,
    "question": "Who was Hiram, called from Tyre for the work?",
    "options": [
     "A craftsman skilled in bronze",
     "A general",
     "A priest",
     "A prophet"
    ],
    "answer": 0
   },
   {
    "id": "1-kgs-7-mc-13",
    "type": "multiple_choice",
    "after_verse": 13,
    "question": "What were the names of the two bronze pillars of the temple porch?",
    "options": [
     "Jachin and Boaz",
     "Sinai and Horeb",
     "David and Solomon",
     "North and South"
    ],
    "answer": 0
   },
   {
    "id": "1-kgs-7-mc-18",
    "type": "multiple_choice",
    "after_verse": 18,
    "question": "What great bronze piece did Hiram make, resting on twelve oxen?",
    "options": [
     "The molten 'sea' (a great basin)",
     "A throne",
     "A golden altar",
     "A statue"
    ],
    "answer": 0
   },
   {
    "id": "1-kgs-7-mc-24",
    "type": "multiple_choice",
    "after_verse": 24,
    "question": "What was the bronze 'sea' for in the temple?",
    "options": [
     "For the priests to wash",
     "To store grain",
     "For sacrifices",
     "For the king's drinking water"
    ],
    "answer": 0
   },
   {
    "id": "1-kgs-7-mc-29",
    "type": "multiple_choice",
    "after_verse": 29,
    "question": "What other bronze pieces were made for the temple?",
    "options": [
     "Ten bases with lavers (basins)",
     "Twelve altars",
     "Four thrones",
     "A single lampstand"
    ],
    "answer": 0
   },
   {
    "id": "1-kgs-7-mc-35",
    "type": "multiple_choice",
    "after_verse": 35,
    "question": "Of what material were the temple's sacred vessels?",
    "options": [
     "Of gold",
     "Of clay",
     "Of iron",
     "Of silver only"
    ],
    "answer": 0
   },
   {
    "id": "1-kgs-7-mc-38",
    "type": "multiple_choice",
    "after_verse": 38,
    "question": "Who made all these metal works for the temple?",
    "options": [
     "Hiram, the craftsman of Tyre",
     "Solomon himself",
     "The Levites",
     "Egyptians"
    ],
    "answer": 0
   },
   {
    "id": "1-kgs-7-mc-43",
    "type": "multiple_choice",
    "after_verse": 43,
    "question": "What did Solomon store when the work was finished?",
    "options": [
     "The treasures David had dedicated",
     "The neighbors' idols",
     "The army's weapons",
     "Egypt's tribute"
    ],
    "answer": 0
   },
   {
    "id": "1-kgs-7-mc-48",
    "type": "multiple_choice",
    "after_verse": 48,
    "question": "What does chapter 7 describe in detail?",
    "options": [
     "The building of the palace and the temple's furnishings",
     "Solomon's wars",
     "The division of the kingdom",
     "The Queen of Sheba"
    ],
    "answer": 0
   }
  ],
  "8": [
   {
    "id": "1-kgs-8-cur-10",
    "type": "curiosity",
    "after_verse": 10,
    "title": "The glory that filled the temple",
    "text": "When the priests came out, a cloud filled the temple: the glory of the Lord was so intense they could not stand to minister. God had accepted the house."
   },
   {
    "id": "1-kgs-8-mc-3",
    "type": "multiple_choice",
    "after_verse": 3,
    "question": "What did the priests bring into the Holy of Holies at the dedication?",
    "options": [
     "The ark of the covenant",
     "David's throne",
     "The conquered idols",
     "Elijah's mantle"
    ],
    "answer": 0
   },
   {
    "id": "1-kgs-8-mc-9",
    "type": "multiple_choice",
    "after_verse": 9,
    "question": "What was inside the ark?",
    "options": [
     "The two stone tablets of Moses",
     "Gold and silver",
     "Aaron's rod",
     "A book of laws"
    ],
    "answer": 0
   },
   {
    "id": "1-kgs-8-mc-15",
    "type": "multiple_choice",
    "after_verse": 15,
    "question": "What filled the temple when the priests came out?",
    "options": [
     "A cloud — the glory of the Lord",
     "Incense smoke",
     "A choir of angels",
     "Sunlight"
    ],
    "answer": 0
   },
   {
    "id": "1-kgs-8-mc-20",
    "type": "multiple_choice",
    "after_verse": 20,
    "question": "What did Solomon recall as he blessed the people?",
    "options": [
     "The promise made to David, now fulfilled",
     "Past wars",
     "Only the exodus from Egypt",
     "The division of the tribes"
    ],
    "answer": 0
   },
   {
    "id": "1-kgs-8-mc-26",
    "type": "multiple_choice",
    "after_verse": 26,
    "question": "What question did Solomon ask in his prayer?",
    "options": [
     "'Will God dwell on the earth?', for the heavens cannot contain Him",
     "'Who is like Thee?'",
     "'Where is the ark?'",
     "'When will the Messiah come?'"
    ],
    "answer": 0
   },
   {
    "id": "1-kgs-8-mc-31",
    "type": "multiple_choice",
    "after_verse": 31,
    "question": "What did Solomon ask about prayers made toward the temple?",
    "options": [
     "That God hear them from heaven and forgive",
     "That they be silent",
     "That only priests pray",
     "That they be in Latin"
    ],
    "answer": 0
   },
   {
    "id": "1-kgs-8-mc-35",
    "type": "multiple_choice",
    "after_verse": 35,
    "question": "What did Solomon ask for times of drought and famine?",
    "options": [
     "That God hear and forgive the repentant people",
     "That He send armies",
     "That He change the king",
     "That He destroy the enemies"
    ],
    "answer": 0
   },
   {
    "id": "1-kgs-8-mc-39",
    "type": "multiple_choice",
    "after_verse": 39,
    "question": "For whom else did Solomon pray, besides Israel?",
    "options": [
     "For the foreigner who would come to pray at the temple",
     "For neighboring kings",
     "For himself",
     "For the priests only"
    ],
    "answer": 0
   },
   {
    "id": "1-kgs-8-mc-43",
    "type": "multiple_choice",
    "after_verse": 43,
    "question": "What did Solomon ask for when the people sinned and were carried captive?",
    "options": [
     "That, repenting, God hear and forgive them",
     "That they never return",
     "That they be destroyed",
     "That another king save them"
    ],
    "answer": 0
   },
   {
    "id": "1-kgs-8-mc-49",
    "type": "multiple_choice",
    "after_verse": 49,
    "question": "How did Solomon describe Israel before God in the prayer?",
    "options": [
     "As an inheritance God brought out of Egypt",
     "As the greatest empire",
     "As a guiltless people",
     "As an invincible army"
    ],
    "answer": 0
   },
   {
    "id": "1-kgs-8-mc-54",
    "type": "multiple_choice",
    "after_verse": 54,
    "question": "What did Solomon do when he finished the long prayer?",
    "options": [
     "He blessed all the congregation of Israel",
     "He crowned a successor",
     "He went to war",
     "He offered himself as a priest"
    ],
    "answer": 0
   },
   {
    "id": "1-kgs-8-mc-58",
    "type": "multiple_choice",
    "after_verse": 58,
    "question": "What did Solomon ask the people's heart to be?",
    "options": [
     "Wholly the Lord's, keeping His commandments",
     "Set on riches",
     "Fearful of kings",
     "Forgetful of the past"
    ],
    "answer": 0
   },
   {
    "id": "1-kgs-8-mc-63",
    "type": "multiple_choice",
    "after_verse": 63,
    "question": "How did the dedication of the temple end?",
    "options": [
     "With many sacrifices and a great feast",
     "In silence",
     "With a battle",
     "With Solomon's departure"
    ],
    "answer": 0
   }
  ],
  "9": [
   {
    "id": "1-kgs-9-cur-3",
    "type": "curiosity",
    "after_verse": 3,
    "title": "'Mine eyes shall be there'",
    "text": "God said He had hallowed the temple and that 'mine eyes and mine heart shall be there perpetually' — but this depended on the faithfulness of Solomon and the people."
   },
   {
    "id": "1-kgs-9-mc-3",
    "type": "multiple_choice",
    "after_verse": 3,
    "question": "What did the Lord do after Solomon finished the temple?",
    "options": [
     "He appeared to him again, accepting the house",
     "He ordered it destroyed",
     "He kept silent",
     "He told him to build another"
    ],
    "answer": 0
   },
   {
    "id": "1-kgs-9-mc-9",
    "type": "multiple_choice",
    "after_verse": 9,
    "question": "What warning did God give Solomon?",
    "options": [
     "That if they turned to other gods, Israel and the temple would be destroyed",
     "That he would live a thousand years",
     "That He would double his riches",
     "That he would never be attacked"
    ],
    "answer": 0
   },
   {
    "id": "1-kgs-9-mc-14",
    "type": "multiple_choice",
    "after_verse": 14,
    "question": "What did Solomon give Hiram, which displeased him?",
    "options": [
     "Twenty cities in Galilee",
     "Half of Jerusalem",
     "The temple",
     "Pharaoh's daughter"
    ],
    "answer": 0
   },
   {
    "id": "1-kgs-9-mc-20",
    "type": "multiple_choice",
    "after_verse": 20,
    "question": "How did Solomon carry out his great building projects?",
    "options": [
     "With forced labor of non-Israelite peoples",
     "With volunteers only",
     "With Egyptian soldiers",
     "Alone"
    ],
    "answer": 0
   },
   {
    "id": "1-kgs-9-mc-25",
    "type": "multiple_choice",
    "after_verse": 25,
    "question": "What did Solomon's fleet bring from Ophir?",
    "options": [
     "A great quantity of gold",
     "Timber",
     "Slaves",
     "Horses"
    ],
    "answer": 0
   }
  ],
  "10": [
   {
    "id": "1-kgs-10-cur-1",
    "type": "curiosity",
    "after_verse": 1,
    "title": "The queen of the South",
    "text": "Jesus would cite 'the queen of the South,' who came from the ends of the earth to hear Solomon's wisdom, as an example of one who seeks truth wholeheartedly (Matthew 12)."
   },
   {
    "id": "1-kgs-10-mc-4",
    "type": "multiple_choice",
    "after_verse": 4,
    "question": "Who came to test Solomon with hard questions?",
    "options": [
     "The Queen of Sheba",
     "Pharaoh's daughter",
     "A prophetess",
     "The queen of Tyre"
    ],
    "answer": 0
   },
   {
    "id": "1-kgs-10-mc-9",
    "type": "multiple_choice",
    "after_verse": 9,
    "question": "How did the Queen of Sheba react on seeing Solomon's wisdom and wealth?",
    "options": [
     "She was overwhelmed: 'the half was not told me'",
     "She laughed",
     "She was indifferent",
     "She accused him of lying"
    ],
    "answer": 0
   },
   {
    "id": "1-kgs-10-mc-15",
    "type": "multiple_choice",
    "after_verse": 15,
    "question": "What did the Queen of Sheba give Solomon?",
    "options": [
     "Gold, spices and precious stones",
     "An army",
     "Lands",
     "Horses"
    ],
    "answer": 0
   },
   {
    "id": "1-kgs-10-mc-20",
    "type": "multiple_choice",
    "after_verse": 20,
    "question": "What was Solomon's throne like?",
    "options": [
     "Of ivory, overlaid with gold",
     "Of stone",
     "Of plain cedar",
     "Of iron"
    ],
    "answer": 0
   },
   {
    "id": "1-kgs-10-mc-26",
    "type": "multiple_choice",
    "after_verse": 26,
    "question": "What was silver like in Solomon's days, it was so abundant?",
    "options": [
     "It was like stones, of little special value",
     "Rare and costly",
     "Forbidden",
     "Used only in the temple"
    ],
    "answer": 0
   }
  ],
  "11": [
   {
    "id": "1-kgs-11-cur-4",
    "type": "curiosity",
    "after_verse": 4,
    "title": "Even the wise can fall",
    "text": "Solomon, the wisest man, turned away by compromising with the idolatry of his foreign wives — a warning that wisdom without faithfulness is not enough."
   },
   {
    "id": "1-kgs-11-mc-3",
    "type": "multiple_choice",
    "after_verse": 3,
    "question": "What turned Solomon's heart away in his old age?",
    "options": [
     "His many foreign wives and their gods",
     "War",
     "Poverty",
     "Pride in the temple"
    ],
    "answer": 0
   },
   {
    "id": "1-kgs-11-mc-8",
    "type": "multiple_choice",
    "after_verse": 8,
    "question": "What did Solomon go so far as to do, in turning away?",
    "options": [
     "He built high places for pagan gods",
     "He destroyed the temple",
     "He abolished the sacrifices",
     "He exiled the priests"
    ],
    "answer": 0
   },
   {
    "id": "1-kgs-11-mc-14",
    "type": "multiple_choice",
    "after_verse": 14,
    "question": "What did the Lord decide because of Solomon's unfaithfulness?",
    "options": [
     "To rend the kingdom, but only after his death",
     "To kill him at once",
     "To destroy Jerusalem immediately",
     "To take away his wisdom"
    ],
    "answer": 0
   },
   {
    "id": "1-kgs-11-mc-19",
    "type": "multiple_choice",
    "after_verse": 19,
    "question": "For whose sake would God leave one tribe to Solomon's house?",
    "options": [
     "For the sake of David and Jerusalem",
     "For Solomon's sake",
     "For the temple's sake",
     "For Hiram's sake"
    ],
    "answer": 0
   },
   {
    "id": "1-kgs-11-mc-24",
    "type": "multiple_choice",
    "after_verse": 24,
    "question": "What adversaries did God raise up against Solomon?",
    "options": [
     "Hadad the Edomite and Rezon",
     "The Philistines",
     "The Ammonites",
     "The Babylonians"
    ],
    "answer": 0
   },
   {
    "id": "1-kgs-11-mc-30",
    "type": "multiple_choice",
    "after_verse": 30,
    "question": "What sign did the prophet Ahijah give Jeroboam?",
    "options": [
     "He tore a garment into twelve pieces and gave him ten",
     "He anointed him with oil",
     "He gave him a sword",
     "He handed him the crown"
    ],
    "answer": 0
   },
   {
    "id": "1-kgs-11-mc-36",
    "type": "multiple_choice",
    "after_verse": 36,
    "question": "What did Ahijah's prophecy mean?",
    "options": [
     "That Jeroboam would reign over ten tribes of Israel",
     "That Solomon would live longer",
     "That the temple would fall",
     "That Rehoboam would be just"
    ],
    "answer": 0
   },
   {
    "id": "1-kgs-11-mc-41",
    "type": "multiple_choice",
    "after_verse": 41,
    "question": "What happened at the end of Solomon's reign?",
    "options": [
     "He died and his son Rehoboam reigned in his place",
     "The kingdom fell at once",
     "Jeroboam killed him",
     "The Philistines won"
    ],
    "answer": 0
   }
  ],
  "12": [
   {
    "id": "1-kgs-12-cur-26",
    "type": "curiosity",
    "after_verse": 26,
    "title": "The 'sin of Jeroboam'",
    "text": "So the north wouldn't go up to Jerusalem, Jeroboam made two golden calves (at Beth-el and Dan). This idolatry, the 'sin of Jeroboam,' condemns king after king in the book."
   },
   {
    "id": "1-kgs-12-mc-3",
    "type": "multiple_choice",
    "after_verse": 3,
    "question": "Where did Rehoboam go to be made king?",
    "options": [
     "To Shechem",
     "To Jerusalem",
     "To Hebron",
     "To Beth-el"
    ],
    "answer": 0
   },
   {
    "id": "1-kgs-12-mc-8",
    "type": "multiple_choice",
    "after_verse": 8,
    "question": "What did the people ask of Rehoboam?",
    "options": [
     "To lighten Solomon's heavy yoke",
     "More taxes",
     "A war",
     "A new temple"
    ],
    "answer": 0
   },
   {
    "id": "1-kgs-12-mc-14",
    "type": "multiple_choice",
    "after_verse": 14,
    "question": "What counsel did Rehoboam follow, angering the people?",
    "options": [
     "The young men's, answering harshly",
     "The elders'",
     "A prophet's",
     "His mother's"
    ],
    "answer": 0
   },
   {
    "id": "1-kgs-12-mc-19",
    "type": "multiple_choice",
    "after_verse": 19,
    "question": "What did Israel do in the face of Rehoboam's harshness?",
    "options": [
     "It rebelled: 'To your tents, O Israel!'",
     "It submitted",
     "It crowned another son of Solomon",
     "It fled to Egypt"
    ],
    "answer": 0
   },
   {
    "id": "1-kgs-12-mc-24",
    "type": "multiple_choice",
    "after_verse": 24,
    "question": "How was the kingdom divided?",
    "options": [
     "Ten tribes with Jeroboam; Judah and Benjamin with Rehoboam",
     "Into three parts",
     "Equally",
     "Unchanged"
    ],
    "answer": 0
   },
   {
    "id": "1-kgs-12-mc-28",
    "type": "multiple_choice",
    "after_verse": 28,
    "question": "What did Jeroboam do so the north would not worship in Jerusalem?",
    "options": [
     "He made two golden calves, at Beth-el and Dan",
     "He built a rival temple",
     "He banned religion",
     "He allied with Egypt"
    ],
    "answer": 0
   },
   {
    "id": "1-kgs-12-mc-31",
    "type": "multiple_choice",
    "after_verse": 31,
    "question": "What else did Jeroboam institute, leading the people astray?",
    "options": [
     "His own priests and feasts, outside the Law",
     "A new army",
     "A law code",
     "A fleet"
    ],
    "answer": 0
   }
  ],
  "13": [
   {
    "id": "1-kgs-13-cur-1",
    "type": "curiosity",
    "after_verse": 1,
    "title": "Obeying the word of God",
    "text": "The man of God performed mighty signs, yet died for disobeying a clear command of the Lord. The chapter teaches that neither gifts nor miracles replace obedience."
   },
   {
    "id": "1-kgs-13-mc-3",
    "type": "multiple_choice",
    "after_verse": 3,
    "question": "What did the man of God prophesy against at Beth-el?",
    "options": [
     "Against Jeroboam's idolatrous altar",
     "Against the temple in Jerusalem",
     "Against Syria",
     "Against Rehoboam"
    ],
    "answer": 0
   },
   {
    "id": "1-kgs-13-mc-8",
    "type": "multiple_choice",
    "after_verse": 8,
    "question": "What happened to Jeroboam's hand when he stretched it out against the prophet?",
    "options": [
     "It dried up, then was restored",
     "It turned to gold",
     "Nothing happened",
     "It was cut off"
    ],
    "answer": 0
   },
   {
    "id": "1-kgs-13-mc-12",
    "type": "multiple_choice",
    "after_verse": 12,
    "question": "What had the man of God been commanded not to do?",
    "options": [
     "Not eat or drink there, nor return by the same way",
     "Not speak to the king",
     "Not pray",
     "Not wear sandals"
    ],
    "answer": 0
   },
   {
    "id": "1-kgs-13-mc-17",
    "type": "multiple_choice",
    "after_verse": 17,
    "question": "Who deceived the man of God into returning to eat?",
    "options": [
     "An old prophet of Beth-el",
     "Jeroboam",
     "An angel",
     "The king of Syria"
    ],
    "answer": 0
   },
   {
    "id": "1-kgs-13-mc-22",
    "type": "multiple_choice",
    "after_verse": 22,
    "question": "What happened to the man of God for disobeying?",
    "options": [
     "He was killed by a lion on the way",
     "He fell ill",
     "He was imprisoned",
     "He lost his gift"
    ],
    "answer": 0
   },
   {
    "id": "1-kgs-13-mc-27",
    "type": "multiple_choice",
    "after_verse": 27,
    "question": "What did the lion do that was unusual beside the body?",
    "options": [
     "It stood by, not devouring the body or the donkey",
     "It fled",
     "It attacked the city",
     "It devoured everything"
    ],
    "answer": 0
   },
   {
    "id": "1-kgs-13-mc-32",
    "type": "multiple_choice",
    "after_verse": 32,
    "question": "What did Jeroboam do after this sign?",
    "options": [
     "He did not turn from his evil way",
     "He repented",
     "He destroyed the calves",
     "He went to Jerusalem"
    ],
    "answer": 0
   }
  ],
  "14": [
   {
    "id": "1-kgs-14-cur-1",
    "type": "curiosity",
    "after_verse": 1,
    "title": "The measure of the northern kings",
    "text": "From here on, nearly every king of Israel is judged by walking 'in the sin of Jeroboam' — the calf idolatry that split the worship of God."
   },
   {
    "id": "1-kgs-14-mc-4",
    "type": "multiple_choice",
    "after_verse": 4,
    "question": "Why did Jeroboam's wife go disguised to the prophet Ahijah?",
    "options": [
     "To learn what would happen to their sick son",
     "To ask for money",
     "To kill him",
     "To spy on him"
    ],
    "answer": 0
   },
   {
    "id": "1-kgs-14-mc-9",
    "type": "multiple_choice",
    "after_verse": 9,
    "question": "What did the blind Ahijah prophesy to Jeroboam's house?",
    "options": [
     "That it would be destroyed because of its idolatry",
     "That it would reign a thousand years",
     "That it would rule Judah",
     "That it would make peace"
    ],
    "answer": 0
   },
   {
    "id": "1-kgs-14-mc-14",
    "type": "multiple_choice",
    "after_verse": 14,
    "question": "What would happen to Jeroboam's sick son?",
    "options": [
     "He would die as soon as his mother entered the city",
     "He would be healed",
     "He would be king",
     "He would flee"
    ],
    "answer": 0
   },
   {
    "id": "1-kgs-14-mc-17",
    "type": "multiple_choice",
    "after_verse": 17,
    "question": "What in fact happened to the son, fulfilling the prophecy?",
    "options": [
     "He died when his mother arrived, and all Israel mourned him",
     "He was healed",
     "He became king",
     "He was hidden away"
    ],
    "answer": 0
   },
   {
    "id": "1-kgs-14-mc-20",
    "type": "multiple_choice",
    "after_verse": 20,
    "question": "What was Rehoboam's reign like in Judah?",
    "options": [
     "He did evil, with high places and idols",
     "It was exemplary",
     "He restored the temple",
     "He abolished idolatry"
    ],
    "answer": 0
   },
   {
    "id": "1-kgs-14-mc-25",
    "type": "multiple_choice",
    "after_verse": 25,
    "question": "Who invaded Judah and plundered the temple in Rehoboam's time?",
    "options": [
     "Shishak, king of Egypt",
     "Ben-hadad",
     "Jeroboam",
     "The Philistines"
    ],
    "answer": 0
   },
   {
    "id": "1-kgs-14-mc-29",
    "type": "multiple_choice",
    "after_verse": 29,
    "question": "What did Rehoboam make in place of the gold shields taken away?",
    "options": [
     "Bronze shields",
     "He rebuilt the temple",
     "He asked Syria for help",
     "He surrendered"
    ],
    "answer": 0
   }
  ],
  "15": [
   {
    "id": "1-kgs-15-cur-11",
    "type": "curiosity",
    "after_verse": 11,
    "title": "Asa, a whole heart",
    "text": "Among so many wicked kings, Asa of Judah stands out: he removed the idols and his heart was 'perfect toward the Lord' all his life — a rare good example."
   },
   {
    "id": "1-kgs-15-mc-4",
    "type": "multiple_choice",
    "after_verse": 4,
    "question": "Who was Asa, king of Judah, in this chapter?",
    "options": [
     "A king who did right and removed idols",
     "A worshiper of Baal",
     "A usurper",
     "An ally of Jeroboam"
    ],
    "answer": 0
   },
   {
    "id": "1-kgs-15-mc-9",
    "type": "multiple_choice",
    "after_verse": 9,
    "question": "What was Asa's heart like toward the Lord?",
    "options": [
     "Perfect (whole) all his days",
     "Divided",
     "Hardened",
     "Indifferent"
    ],
    "answer": 0
   },
   {
    "id": "1-kgs-15-mc-15",
    "type": "multiple_choice",
    "after_verse": 15,
    "question": "With whom did Asa make a league against Baasha of Israel?",
    "options": [
     "With the king of Syria",
     "With Egypt",
     "With the Philistines",
     "With Tyre"
    ],
    "answer": 0
   },
   {
    "id": "1-kgs-15-mc-21",
    "type": "multiple_choice",
    "after_verse": 21,
    "question": "Who reigned in Israel after Jeroboam, doing evil?",
    "options": [
     "Nadab, his son",
     "Asa",
     "Omri",
     "Ahab"
    ],
    "answer": 0
   },
   {
    "id": "1-kgs-15-mc-27",
    "type": "multiple_choice",
    "after_verse": 27,
    "question": "Who killed Nadab and destroyed Jeroboam's house?",
    "options": [
     "Baasha",
     "Zimri",
     "Omri",
     "Elisha"
    ],
    "answer": 0
   },
   {
    "id": "1-kgs-15-mc-32",
    "type": "multiple_choice",
    "after_verse": 32,
    "question": "What did the destruction of Jeroboam's house fulfill?",
    "options": [
     "The prophecy of Ahijah",
     "A dream of Asa",
     "The law of Moses",
     "A request of the people"
    ],
    "answer": 0
   }
  ],
  "16": [
   {
    "id": "1-kgs-16-cur-30",
    "type": "curiosity",
    "after_verse": 30,
    "title": "Ahab and Jezebel",
    "text": "Ahab was worse than all the kings before him: he married Jezebel, princess of Sidon, and established Baal worship in Israel — which will provoke Elijah's ministry."
   },
   {
    "id": "1-kgs-16-mc-3",
    "type": "multiple_choice",
    "after_verse": 3,
    "question": "What pattern recurs among the kings of Israel in this chapter?",
    "options": [
     "They do evil, following the sin of Jeroboam",
     "They are all righteous",
     "They worship only the Lord",
     "They reign in peace"
    ],
    "answer": 0
   },
   {
    "id": "1-kgs-16-mc-8",
    "type": "multiple_choice",
    "after_verse": 8,
    "question": "Who killed Elah and seized the throne for only seven days?",
    "options": [
     "Zimri",
     "Omri",
     "Baasha",
     "Ahab"
    ],
    "answer": 0
   },
   {
    "id": "1-kgs-16-mc-12",
    "type": "multiple_choice",
    "after_verse": 12,
    "question": "What did Zimri do when he saw himself surrounded and lost?",
    "options": [
     "He burned the palace down over himself",
     "He fled to Syria",
     "He surrendered",
     "He begged forgiveness"
    ],
    "answer": 0
   },
   {
    "id": "1-kgs-16-mc-17",
    "type": "multiple_choice",
    "after_verse": 17,
    "question": "Who became king and founded the city of Samaria?",
    "options": [
     "Omri",
     "Zimri",
     "Ahab",
     "Jehu"
    ],
    "answer": 0
   },
   {
    "id": "1-kgs-16-mc-23",
    "type": "multiple_choice",
    "after_verse": 23,
    "question": "How does the chapter describe Ahab, son of Omri?",
    "options": [
     "He did evil more than all the kings before him",
     "He was the most righteous",
     "He restored the temple",
     "He was a prophet"
    ],
    "answer": 0
   },
   {
    "id": "1-kgs-16-mc-28",
    "type": "multiple_choice",
    "after_verse": 28,
    "question": "Whom did Ahab marry, deepening the idolatry?",
    "options": [
     "Jezebel, and he came to serve Baal",
     "Pharaoh's daughter",
     "The Queen of Sheba",
     "A daughter of Asa"
    ],
    "answer": 0
   },
   {
    "id": "1-kgs-16-mc-32",
    "type": "multiple_choice",
    "after_verse": 32,
    "question": "What did Ahab build for Baal in Samaria?",
    "options": [
     "A temple and an altar",
     "A school",
     "A palace",
     "A wall"
    ],
    "answer": 0
   }
  ],
  "17": [
   {
    "id": "1-kgs-17-cur-1",
    "type": "curiosity",
    "after_verse": 1,
    "title": "Elijah against Baal",
    "text": "The drought Elijah announced was a direct blow against Baal, worshiped as the god of rain and fertility: the Lord would show who really governs the sky and life."
   },
   {
    "id": "1-kgs-17-mc-3",
    "type": "multiple_choice",
    "after_verse": 3,
    "question": "What did Elijah announce to king Ahab?",
    "options": [
     "That there would be no dew or rain except by his word",
     "An invasion",
     "An earthquake",
     "The king's death"
    ],
    "answer": 0
   },
   {
    "id": "1-kgs-17-mc-8",
    "type": "multiple_choice",
    "after_verse": 8,
    "question": "How was Elijah fed by the brook Cherith?",
    "options": [
     "By ravens, which brought him bread and meat",
     "By angels",
     "By fishermen",
     "By a king"
    ],
    "answer": 0
   },
   {
    "id": "1-kgs-17-mc-13",
    "type": "multiple_choice",
    "after_verse": 13,
    "question": "What miracle happened at the house of the widow of Zarephath?",
    "options": [
     "The meal and oil did not run out during the drought",
     "It rained gold",
     "The house never aged",
     "A well appeared"
    ],
    "answer": 0
   },
   {
    "id": "1-kgs-17-mc-18",
    "type": "multiple_choice",
    "after_verse": 18,
    "question": "What happened to the son of the widow of Zarephath?",
    "options": [
     "He fell sick and died",
     "He became a prophet",
     "He was taken to the king",
     "He vanished"
    ],
    "answer": 0
   },
   {
    "id": "1-kgs-17-mc-22",
    "type": "multiple_choice",
    "after_verse": 22,
    "question": "What did Elijah do for the widow's dead son?",
    "options": [
     "He prayed, and the Lord raised him to life",
     "He buried him",
     "He took him to Ahab",
     "He could do nothing"
    ],
    "answer": 0
   }
  ],
  "18": [
   {
    "id": "1-kgs-18-cur-20",
    "type": "curiosity",
    "after_verse": 20,
    "title": "'How long halt ye between two opinions?'",
    "text": "On Carmel, Elijah challenged the people: 'How long halt ye between two opinions? If the Lord be God, follow him; but if Baal, then him.' It was time to decide."
   },
   {
    "id": "1-kgs-18-mc-3",
    "type": "multiple_choice",
    "after_verse": 3,
    "question": "Whom did Elijah meet before Ahab, who had hidden prophets of the Lord?",
    "options": [
     "Obadiah, Ahab's steward",
     "Elisha",
     "Jezebel",
     "Micaiah"
    ],
    "answer": 0
   },
   {
    "id": "1-kgs-18-mc-8",
    "type": "multiple_choice",
    "after_verse": 8,
    "question": "What did Ahab call Elijah when he met him?",
    "options": [
     "'The troubler of Israel'",
     "'Man of God'",
     "'Prophet of peace'",
     "'Friend of the king'"
    ],
    "answer": 0
   },
   {
    "id": "1-kgs-18-mc-13",
    "type": "multiple_choice",
    "after_verse": 13,
    "question": "What challenge did Elijah propose on Mount Carmel?",
    "options": [
     "To see which God would answer by fire: the Lord or Baal",
     "A battle",
     "A fast",
     "A race"
    ],
    "answer": 0
   },
   {
    "id": "1-kgs-18-mc-16",
    "type": "multiple_choice",
    "after_verse": 16,
    "question": "How many prophets of Baal did Elijah face alone?",
    "options": [
     "Four hundred and fifty",
     "Twelve",
     "Seventy",
     "A thousand"
    ],
    "answer": 0
   },
   {
    "id": "1-kgs-18-mc-21",
    "type": "multiple_choice",
    "after_verse": 21,
    "question": "What did the prophets of Baal do, in vain, to make their god answer?",
    "options": [
     "They cried out and cut themselves, but there was no answer",
     "They prayed in silence",
     "They offered gold",
     "They built a bigger altar"
    ],
    "answer": 0
   },
   {
    "id": "1-kgs-18-mc-25",
    "type": "multiple_choice",
    "after_verse": 25,
    "question": "What did Elijah do to his altar before praying?",
    "options": [
     "He soaked it with water three times",
     "He covered it with gold",
     "He hid it",
     "He burned it beforehand"
    ],
    "answer": 0
   },
   {
    "id": "1-kgs-18-mc-31",
    "type": "multiple_choice",
    "after_verse": 31,
    "question": "What happened when Elijah prayed to the Lord?",
    "options": [
     "Fire fell from heaven and consumed everything",
     "It rained at once",
     "The earth shook",
     "Nothing"
    ],
    "answer": 0
   },
   {
    "id": "1-kgs-18-mc-36",
    "type": "multiple_choice",
    "after_verse": 36,
    "question": "What did the people cry out when they saw the fire from heaven?",
    "options": [
     "'The Lord, he is God! The Lord, he is God!'",
     "'Long live Baal'",
     "'Long live the king'",
     "They were silent"
    ],
    "answer": 0
   },
   {
    "id": "1-kgs-18-mc-40",
    "type": "multiple_choice",
    "after_verse": 40,
    "question": "What happened to the prophets of Baal after the challenge?",
    "options": [
     "They were put to death",
     "They fled",
     "They were converted",
     "They were imprisoned"
    ],
    "answer": 0
   },
   {
    "id": "1-kgs-18-mc-44",
    "type": "multiple_choice",
    "after_verse": 44,
    "question": "What did Elijah announce after the challenge ended?",
    "options": [
     "The return of the rain, after praying seven times",
     "Another drought",
     "Ahab's death",
     "A war"
    ],
    "answer": 0
   }
  ],
  "19": [
   {
    "id": "1-kgs-19-cur-18",
    "type": "curiosity",
    "after_verse": 18,
    "title": "Seven thousand who had not bowed",
    "text": "Elijah thought he was alone, but God revealed there were 7,000 in Israel who had not bowed their knees to Baal — he was not alone in faithfulness."
   },
   {
    "id": "1-kgs-19-mc-4",
    "type": "multiple_choice",
    "after_verse": 4,
    "question": "What led Elijah to flee to the wilderness, discouraged?",
    "options": [
     "Jezebel's threat to kill him",
     "A defeat at Carmel",
     "Famine",
     "The loss of Elisha"
    ],
    "answer": 0
   },
   {
    "id": "1-kgs-19-mc-9",
    "type": "multiple_choice",
    "after_verse": 9,
    "question": "How was Elijah sustained on the way to Horeb?",
    "options": [
     "An angel fed him",
     "Ravens served him",
     "He found a feast",
     "He fasted without food"
    ],
    "answer": 0
   },
   {
    "id": "1-kgs-19-mc-15",
    "type": "multiple_choice",
    "after_verse": 15,
    "question": "Where was the Lord, and not in the wind, earthquake or fire?",
    "options": [
     "In a still small voice",
     "In a thunderstorm",
     "In a cloud",
     "In a dream"
    ],
    "answer": 0
   },
   {
    "id": "1-kgs-19-mc-19",
    "type": "multiple_choice",
    "after_verse": 19,
    "question": "Whom did Elijah call to be his successor, finding him plowing?",
    "options": [
     "Elisha",
     "Jehu",
     "Hazael",
     "Obadiah"
    ],
    "answer": 0
   }
  ],
  "20": [
   {
    "id": "1-kgs-20-cur-28",
    "type": "curiosity",
    "after_verse": 28,
    "title": "God of hills and valleys",
    "text": "The Syrians said Israel's God was 'a god of the hills,' not of the valleys. God gave the victory in the valley precisely to show that he reigns over all."
   },
   {
    "id": "1-kgs-20-mc-3",
    "type": "multiple_choice",
    "after_verse": 3,
    "question": "Who besieged Samaria, demanding Ahab's surrender?",
    "options": [
     "Ben-hadad, king of Syria",
     "Shishak of Egypt",
     "The Philistines",
     "Jeroboam"
    ],
    "answer": 0
   },
   {
    "id": "1-kgs-20-mc-9",
    "type": "multiple_choice",
    "after_verse": 9,
    "question": "What did a prophet announce to Ahab about the battle?",
    "options": [
     "That the Lord would deliver the Syrians into his hand",
     "That he would lose",
     "That he should flee",
     "That he should pay tribute"
    ],
    "answer": 0
   },
   {
    "id": "1-kgs-20-mc-14",
    "type": "multiple_choice",
    "after_verse": 14,
    "question": "What was the result of the first clash with Syria?",
    "options": [
     "Israel won",
     "Israel lost",
     "There was a truce",
     "Samaria fell"
    ],
    "answer": 0
   },
   {
    "id": "1-kgs-20-mc-20",
    "type": "multiple_choice",
    "after_verse": 20,
    "question": "What did the Syrians say about the God of Israel?",
    "options": [
     "That he was 'a god of the hills,' not of the valleys",
     "That he was invincible",
     "That he did not exist",
     "That he was the same as Baal"
    ],
    "answer": 0
   },
   {
    "id": "1-kgs-20-mc-25",
    "type": "multiple_choice",
    "after_verse": 25,
    "question": "What happened in the second battle, fought in the valley?",
    "options": [
     "Israel won again, showing God's power",
     "Israel was destroyed",
     "It was a draw",
     "Syria took Samaria"
    ],
    "answer": 0
   },
   {
    "id": "1-kgs-20-mc-30",
    "type": "multiple_choice",
    "after_verse": 30,
    "question": "What did Ahab do with Ben-hadad on defeating him?",
    "options": [
     "He spared him and made a covenant",
     "He killed him",
     "He exiled him",
     "He crowned him"
    ],
    "answer": 0
   },
   {
    "id": "1-kgs-20-mc-35",
    "type": "multiple_choice",
    "after_verse": 35,
    "question": "What did a prophet do to rebuke Ahab?",
    "options": [
     "He pretended to be wounded and led Ahab to judge himself",
     "He attacked him",
     "He cursed him publicly",
     "He fled"
    ],
    "answer": 0
   },
   {
    "id": "1-kgs-20-mc-41",
    "type": "multiple_choice",
    "after_verse": 41,
    "question": "What did the prophet announce to Ahab for sparing Ben-hadad?",
    "options": [
     "That his life would answer for the king he had released",
     "That he would reign longer",
     "That he would defeat Syria",
     "That he would have peace"
    ],
    "answer": 0
   }
  ],
  "21": [
   {
    "id": "1-kgs-21-cur-3",
    "type": "curiosity",
    "after_verse": 3,
    "title": "Naboth's inheritance",
    "text": "Naboth refused to sell the vineyard because it was his fathers' inheritance, sacred under Israel's Law. For this Jezebel had him killed — a crime of greed and injustice."
   },
   {
    "id": "1-kgs-21-mc-3",
    "type": "multiple_choice",
    "after_verse": 3,
    "question": "What did Ahab covet from Naboth?",
    "options": [
     "His vineyard, near the palace",
     "His house",
     "His flock",
     "His daughter"
    ],
    "answer": 0
   },
   {
    "id": "1-kgs-21-mc-9",
    "type": "multiple_choice",
    "after_verse": 9,
    "question": "Why did Naboth refuse to sell the vineyard to Ahab?",
    "options": [
     "It was his fathers' inheritance",
     "He wanted more money",
     "He was afraid",
     "He had already sold it"
    ],
    "answer": 0
   },
   {
    "id": "1-kgs-21-mc-14",
    "type": "multiple_choice",
    "after_verse": 14,
    "question": "What did Jezebel plot so Ahab could have the vineyard?",
    "options": [
     "She falsely accused Naboth and had him stoned",
     "She bought it",
     "She threatened him",
     "She burned it"
    ],
    "answer": 0
   },
   {
    "id": "1-kgs-21-mc-18",
    "type": "multiple_choice",
    "after_verse": 18,
    "question": "What did Elijah say to Ahab about the crime?",
    "options": [
     "'Hast thou killed, and also taken possession?'",
     "'Go in peace'",
     "'Build an altar'",
     "'Flee the city'"
    ],
    "answer": 0
   },
   {
    "id": "1-kgs-21-mc-22",
    "type": "multiple_choice",
    "after_verse": 22,
    "question": "What judgment did Elijah announce on Ahab's house?",
    "options": [
     "That it would be destroyed, and dogs would eat Jezebel",
     "That it would reign forever",
     "That he would defeat Syria",
     "That he would have many children"
    ],
    "answer": 0
   },
   {
    "id": "1-kgs-21-mc-27",
    "type": "multiple_choice",
    "after_verse": 27,
    "question": "What happened when Ahab humbled himself before God?",
    "options": [
     "God delayed the punishment to his son's days",
     "He was fully pardoned",
     "He recovered the vineyard",
     "He died at once"
    ],
    "answer": 0
   }
  ],
  "22": [
   {
    "id": "1-kgs-22-cur-28",
    "type": "curiosity",
    "after_verse": 28,
    "title": "Micaiah, alone against 400",
    "text": "While 400 prophets flattered Ahab, only Micaiah dared to tell the uncomfortable truth — an example of faithfulness that cost dearly, but came to pass."
   },
   {
    "id": "1-kgs-22-mc-3",
    "type": "multiple_choice",
    "after_verse": 3,
    "question": "What did Jehoshaphat, king of Judah, propose to Ahab?",
    "options": [
     "To ally to retake Ramoth-gilead",
     "To build a temple",
     "To divide the kingdom",
     "To attack Egypt"
    ],
    "answer": 0
   },
   {
    "id": "1-kgs-22-mc-8",
    "type": "multiple_choice",
    "after_verse": 8,
    "question": "What did Ahab's 400 prophets say about the battle?",
    "options": [
     "To go up, for he would win",
     "That he would lose",
     "To wait",
     "To make peace"
    ],
    "answer": 0
   },
   {
    "id": "1-kgs-22-mc-13",
    "type": "multiple_choice",
    "after_verse": 13,
    "question": "Whom did Jehoshaphat ask to consult, a prophet of the Lord?",
    "options": [
     "Micaiah",
     "Elijah",
     "Elisha",
     "Nathan"
    ],
    "answer": 0
   },
   {
    "id": "1-kgs-22-mc-18",
    "type": "multiple_choice",
    "after_verse": 18,
    "question": "What did Micaiah truly prophesy?",
    "options": [
     "Defeat: 'I saw all Israel scattered upon the hills'",
     "Victory",
     "A long peace",
     "Jehoshaphat's death"
    ],
    "answer": 0
   },
   {
    "id": "1-kgs-22-mc-23",
    "type": "multiple_choice",
    "after_verse": 23,
    "question": "How did Micaiah explain the false prophets?",
    "options": [
     "A lying spirit in their mouths, to deceive Ahab",
     "They were right",
     "They were wise",
     "They spoke for God"
    ],
    "answer": 0
   },
   {
    "id": "1-kgs-22-mc-27",
    "type": "multiple_choice",
    "after_verse": 27,
    "question": "What did Ahab do with Micaiah over the prophecy?",
    "options": [
     "He had him imprisoned",
     "He rewarded him",
     "He freed him",
     "He crowned him"
    ],
    "answer": 0
   },
   {
    "id": "1-kgs-22-mc-31",
    "type": "multiple_choice",
    "after_verse": 31,
    "question": "What did Ahab do to try to escape the prophecy in battle?",
    "options": [
     "He disguised himself as an ordinary soldier",
     "He fled",
     "He surrendered",
     "He stayed in Samaria"
    ],
    "answer": 0
   },
   {
    "id": "1-kgs-22-mc-36",
    "type": "multiple_choice",
    "after_verse": 36,
    "question": "How did Ahab die, despite the disguise?",
    "options": [
     "A randomly shot arrow struck him",
     "Of illness",
     "By drowning",
     "At home"
    ],
    "answer": 0
   },
   {
    "id": "1-kgs-22-mc-42",
    "type": "multiple_choice",
    "after_verse": 42,
    "question": "What happened to Ahab's blood, fulfilling the prophecy?",
    "options": [
     "The dogs licked it",
     "It was buried in gold",
     "It vanished",
     "It turned to dust"
    ],
    "answer": 0
   },
   {
    "id": "1-kgs-22-mc-47",
    "type": "multiple_choice",
    "after_verse": 47,
    "question": "What was Jehoshaphat's reign like in Judah?",
    "options": [
     "He walked in the right ways, like Asa his father",
     "He was wicked",
     "He worshiped Baal",
     "It was brief and violent"
    ],
    "answer": 0
   },
   {
    "id": "1-kgs-22-mc-51",
    "type": "multiple_choice",
    "after_verse": 51,
    "question": "Who reigned in Israel after Ahab's death?",
    "options": [
     "Ahaziah, his son, who did evil",
     "Jehu",
     "Elisha",
     "Omri"
    ],
    "answer": 0
   }
  ]
 }
}
